Workbook
Name StartDate: Inputs!$B$3
Name DevMonths: Inputs!$B$4
Name ConMonths: Inputs!$B$5
Name OpYears: Inputs!$B$6
Name MWac: Inputs!$B$9
Name MWp: Inputs!$B$10
Name P50MWh: Inputs!$B$11
Name DegradPct: Inputs!$B$12
Name PPAPrice: Inputs!$B$15
Name PPATerm: Inputs!$B$16
Name MerchantPrice: Inputs!$B$17
Name Indexation: Inputs!$B$18
Name ColCPI: Inputs!$B$19
Name CapexDev: Inputs!$B$22
Name CapexCon: Inputs!$B$23
Name CapexCOD: Inputs!$B$24
Name CapexDist: Inputs!$B$25
Name FixedOM: Inputs!$B$28
Name VarOM: Inputs!$B$29
Name Insurance: Inputs!$B$30
Name GridFees: Inputs!$B$31
Name OpexIndex: Inputs!$B$32
Name DebtEnabled: Inputs!$B$35
Name DebtPct: Inputs!$B$36
Name DebtTenor: Inputs!$B$37
Name DebtRate: Inputs!$B$38
Name DebtAmort: Inputs!$B$39
Name UpfrontFee: Inputs!$B$40
Name CommitFee: Inputs!$B$41
Name TaxRate: Inputs!$B$44
Name DepYears: Inputs!$B$45
Name DepPct: Inputs!$B$46

Sheet Inputs
A1: RENEWABLE PROJECT FINANCIAL MODEL - INPUTS
A3: TIMELINE
A4: Start Date | B4: 45292
A5: Development Months | B5: 18
A6: Construction Months | B6: 12
A7: Operation Years | B7: 25
A9: GENERATION
A10: MWac | B10: 100
A11: MWp | B11: 130
A12: P50 MWh/Year | B12: 220000
A13: Degradation %/Year | B13: 0.5
A15: REVENUE
A16: PPA Price (COP/kWh) | B16: 320
A17: PPA Term (Years) | B17: 12
A18: Merchant Price (COP/kWh) | B18: 250
A19: Indexation | B19: Colombia CPI
A20: Colombia CPI % | B20: 6
A22: CAPEX
A23: Development (COP) | B23: 5000000000
A24: Construction (COP) | B24: 80000000000
A25: At COD (COP) | B25: 5000000000
A26: Distribution | B26: Straight-line
A28: OPEX
A29: Fixed OM (COP/MWac/Year) | B29: 5000000
A30: Variable OM (COP/MWh) | B30: 5000
A31: Insurance (COP/MWac/Year) | B31: 2000000
A32: Grid Fees (COP/MWh) | B32: 10000
A33: OPEX Indexation | B33: Colombia CPI
A35: DEBT
A36: Debt Enabled | B36: Yes
A37: Debt % of CAPEX | B37: 70
A38: Tenor (Years) | B38: 15
A39: All-in Interest Rate % | B39: 8.5
A40: Amortization Method | B40: Equal Principal
A41: Upfront Fee (bps) | B41: 100
A42: Commitment Fee % of Margin | B42: 50
A44: TAX
A45: Corporate Tax Rate % | B45: 35
A46: Depreciation Years | B46: 20
A47: Depreciation % of CAPEX | B47: 100

Sheet Timeline_M
A1: Month | B1: Year | C1: Phase | D1: MonthNum | E1: Total Months
A2: =StartDate | B2: =YEAR(A2) | C2: =IF(MonthNum<=DevMonths,"Development",IF(MonthNum<=DevMonths+ConMonths,"Construction","Operation")) | D2: =ROW()-1 | E2: =DevMonths+ConMonths+OpYears*12
A3: =EDATE(A2,1) | B3: =YEAR(A3) | C3: =IF(D3<=DevMonths,"Development",IF(D3<=DevMonths+ConMonths,"Construction","Operation")) | D3: =ROW()-1
A4: =EDATE(A3,1) | B4: =YEAR(A4) | C4: =IF(D4<=DevMonths,"Development",IF(D4<=DevMonths+ConMonths,"Construction","Operation")) | D4: =ROW()-1
A5: =EDATE(A4,1) | B5: =YEAR(A5) | C5: =IF(D5<=DevMonths,"Development",IF(D5<=DevMonths+ConMonths,"Construction","Operation")) | D5: =ROW()-1
A6: =EDATE(A5,1) | B6: =YEAR(A6) | C6: =IF(D6<=DevMonths,"Development",IF(D6<=DevMonths+ConMonths,"Construction","Operation")) | D6: =ROW()-1
A7: =EDATE(A6,1) | B7: =YEAR(A7) | C7: =IF(D7<=DevMonths,"Development",IF(D7<=DevMonths+ConMonths,"Construction","Operation")) | D7: =ROW()-1
A8: =EDATE(A7,1) | B8: =YEAR(A8) | C8: =IF(D8<=DevMonths,"Development",IF(D8<=DevMonths+ConMonths,"Construction","Operation")) | D8: =ROW()-1
A9: =EDATE(A8,1) | B9: =YEAR(A9) | C9: =IF(D9<=DevMonths,"Development",IF(D9<=DevMonths+ConMonths,"Construction","Operation")) | D9: =ROW()-1
A10: =EDATE(A9,1) | B10: =YEAR(A10) | C10: =IF(D10<=DevMonths,"Development",IF(D10<=DevMonths+ConMonths,"Construction","Operation")) | D10: =ROW()-1
A11: =EDATE(A10,1) | B11: =YEAR(A11) | C11: =IF(D11<=DevMonths,"Development",IF(D11<=DevMonths+ConMonths,"Construction","Operation")) | D11: =ROW()-1
A12: =EDATE(A11,1) | B12: =YEAR(A12) | C12: =IF(D12<=DevMonths,"Development",IF(D12<=DevMonths+ConMonths,"Construction","Operation")) | D12: =ROW()-1
A13: =EDATE(A12,1) | B13: =YEAR(A13) | C13: =IF(D13<=DevMonths,"Development",IF(D13<=DevMonths+ConMonths,"Construction","Operation")) | D13: =ROW()-1
A14: =EDATE(A13,1) | B14: =YEAR(A14) | C14: =IF(D14<=DevMonths,"Development",IF(D14<=DevMonths+ConMonths,"Construction","Operation")) | D14: =ROW()-1
... A500: =EDATE(A499,1) | B500: =YEAR(A500) | C500: =IF(D500<=DevMonths,"Development",IF(D500<=DevMonths+ConMonths,"Construction","Operation")) | D500: =ROW()-1

Sheet CAPEX_M
A1: Month | B1: Year | C1: Phase | D1: CAPEX_Dev | E1: CAPEX_Con | F1: CAPEX_COD | G1: CAPEX_Total
A2: =Timeline_M!A2 | B2: =Timeline_M!B2 | C2: =Timeline_M!C2 | D2: =IF(C2="Development",CapexDev/DevMonths,0) | E2: =IF(C2="Construction",CapexCon/ConMonths,0) | F2: =IF(AND(C2="Operation",Timeline_M!D2=DevMonths+ConMonths+1),CapexCOD,0) | G2: =SUM(D2:F2)
A3: =Timeline_M!A3 | B3: =Timeline_M!B3 | C3: =Timeline_M!C3 | D3: =IF(C3="Development",CapexDev/DevMonths,0) | E3: =IF(C3="Construction",CapexCon/ConMonths,0) | F3: =IF(AND(C3="Operation",Timeline_M!D3=DevMonths+ConMonths+1),CapexCOD,0) | G3: =SUM(D3:F3)
A4: =Timeline_M!A4 | B4: =Timeline_M!B4 | C4: =Timeline_M!C4 | D4: =IF(C4="Development",CapexDev/DevMonths,0) | E4: =IF(C4="Construction",CapexCon/ConMonths,0) | F4: =IF(AND(C4="Operation",Timeline_M!D4=DevMonths+ConMonths+1),CapexCOD,0) | G4: =SUM(D4:F4)
A5: =Timeline_M!A5 | B5: =Timeline_M!B5 | C5: =Timeline_M!C5 | D5: =IF(C5="Development",CapexDev/DevMonths,0) | E5: =IF(C5="Construction",CapexCon/ConMonths,0) | F5: =IF(AND(C5="Operation",Timeline_M!D5=DevMonths+ConMonths+1),CapexCOD,0) | G5: =SUM(D5:F5)
A6: =Timeline_M!A6 | B6: =Timeline_M!B6 | C6: =Timeline_M!C6 | D6: =IF(C6="Development",CapexDev/DevMonths,0) | E6: =IF(C6="Construction",CapexCon/ConMonths,0) | F6: =IF(AND(C6="Operation",Timeline_M!D6=DevMonths+ConMonths+1),CapexCOD,0) | G6: =SUM(D6:F6)
A7: =Timeline_M!A7 | B7: =Timeline_M!B7 | C7: =Timeline_M!C7 | D7: =IF(C7="Development",CapexDev/DevMonths,0) | E7: =IF(C7="Construction",CapexCon/ConMonths,0) | F7: =IF(AND(C7="Operation",Timeline_M!D7=DevMonths+ConMonths+1),CapexCOD,0) | G7: =SUM(D7:F7)
A8: =Timeline_M!A8 | B8: =Timeline_M!B8 | C8: =Timeline_M!C8 | D8: =IF(C8="Development",CapexDev/DevMonths,0) | E8: =IF(C8="Construction",CapexCon/ConMonths,0) | F8: =IF(AND(C8="Operation",Timeline_M!D8=DevMonths+ConMonths+1),CapexCOD,0) | G8: =SUM(D8:F8)
A9: =Timeline_M!A9 | B9: =Timeline_M!B9 | C9: =Timeline_M!C9 | D9: =IF(C9="Development",CapexDev/DevMonths,0) | E9: =IF(C9="Construction",CapexCon/ConMonths,0) | F9: =IF(AND(C9="Operation",Timeline_M!D9=DevMonths+ConMonths+1),CapexCOD,0) | G9: =SUM(D9:F9)
A10: =Timeline_M!A10 | B10: =Timeline_M!B10 | C10: =Timeline_M!C10 | D10: =IF(C10="Development",CapexDev/DevMonths,0) | E10: =IF(C10="Construction",CapexCon/ConMonths,0) | F10: =IF(AND(C10="Operation",Timeline_M!D10=DevMonths+ConMonths+1),CapexCOD,0) | G10: =SUM(D10:F10)
A11: =Timeline_M!A11 | B11: =Timeline_M!B11 | C11: =Timeline_M!C11 | D11: =IF(C11="Development",CapexDev/DevMonths,0) | E11: =IF(C11="Construction",CapexCon/ConMonths,0) | F11: =IF(AND(C11="Operation",Timeline_M!D11=DevMonths+ConMonths+1),CapexCOD,0) | G11: =SUM(D11:F11)
A12: =Timeline_M!A12 | B12: =Timeline_M!B12 | C12: =Timeline_M!C12 | D12: =IF(C12="Development",CapexDev/DevMonths,0) | E12: =IF(C12="Construction",CapexCon/ConMonths,0) | F12: =IF(AND(C12="Operation",Timeline_M!D12=DevMonths+ConMonths+1),CapexCOD,0) | G12: =SUM(D12:F12)
A13: =Timeline_M!A13 | B13: =Timeline_M!B13 | C13: =Timeline_M!C13 | D13: =IF(C13="Development",CapexDev/DevMonths,0) | E13: =IF(C13="Construction",CapexCon/ConMonths,0) | F13: =IF(AND(C13="Operation",Timeline_M!D13=DevMonths+ConMonths+1),CapexCOD,0) | G13: =SUM(D13:F13)
... A500: =Timeline_M!A500 | B500: =Timeline_M!B500 | C500: =Timeline_M!C500 | D500: =IF(C500="Development",CapexDev/DevMonths,0) | E500: =IF(C500="Construction",CapexCon/ConMonths,0) | F500: =IF(AND(C500="Operation",Timeline_M!D500=DevMonths+ConMonths+1),CapexCOD,0) | G500: =SUM(D500:F500)

Sheet Revenue_M
A1: Month | B1: Year | C1: Phase | D1: OperatingYear | E1: Energy_MWh | F1: Price_COP_kWh | G1: Revenue_COP
A2: =Timeline_M!A2 | B2: =Timeline_M!B2 | C2: =Timeline_M!C2 | D2: =IF(C2="Operation",YEAR(A2)-YEAR(EDATE(StartDate,DevMonths+ConMonths))+1,0) | E2: =IF(C2="Operation",(P50MWh*(1-DegradPct/100)^(D2-1))/12,0) | F2: =IF(C2="Operation",IF(D2<=PPATerm,PPAPrice,MerchantPrice)*(1+ColCPI/100)^(D2-1),0) | G2: =E2*F2*1000
A3: =Timeline_M!A3 | B3: =Timeline_M!B3 | C3: =Timeline_M!C3 | D3: =IF(C3="Operation",YEAR(A3)-YEAR(EDATE(StartDate,DevMonths+ConMonths))+1,0) | E3: =IF(C3="Operation",(P50MWh*(1-DegradPct/100)^(D3-1))/12,0) | F3: =IF(C3="Operation",IF(D3<=PPATerm,PPAPrice,MerchantPrice)*(1+ColCPI/100)^(D3-1),0) | G3: =E3*F3*1000
A4: =Timeline_M!A4 | B4: =Timeline_M!B4 | C4: =Timeline_M!C4 | D4: =IF(C4="Operation",YEAR(A4)-YEAR(EDATE(StartDate,DevMonths+ConMonths))+1,0) | E4: =IF(C4="Operation",(P50MWh*(1-DegradPct/100)^(D4-1))/12,0) | F4: =IF(C4="Operation",IF(D4<=PPATerm,PPAPrice,MerchantPrice)*(1+ColCPI/100)^(D4-1),0) | G4: =E4*F4*1000
A5: =Timeline_M!A5 | B5: =Timeline_M!B5 | C5: =Timeline_M!C5 | D5: =IF(C5="Operation",YEAR(A5)-YEAR(EDATE(StartDate,DevMonths+ConMonths))+1,0) | E5: =IF(C5="Operation",(P50MWh*(1-DegradPct/100)^(D5-1))/12,0) | F5: =IF(C5="Operation",IF(D5<=PPATerm,PPAPrice,MerchantPrice)*(1+ColCPI/100)^(D5-1),0) | G5: =E5*F5*1000
A6: =Timeline_M!A6 | B6: =Timeline_M!B6 | C6: =Timeline_M!C6 | D6: =IF(C6="Operation",YEAR(A6)-YEAR(EDATE(StartDate,DevMonths+ConMonths))+1,0) | E6: =IF(C6="Operation",(P50MWh*(1-DegradPct/100)^(D6-1))/12,0) | F6: =IF(C6="Operation",IF(D6<=PPATerm,PPAPrice,MerchantPrice)*(1+ColCPI/100)^(D6-1),0) | G6: =E6*F6*1000
A7: =Timeline_M!A7 | B7: =Timeline_M!B7 | C7: =Timeline_M!C7 | D7: =IF(C7="Operation",YEAR(A7)-YEAR(EDATE(StartDate,DevMonths+ConMonths))+1,0) | E7: =IF(C7="Operation",(P50MWh*(1-DegradPct/100)^(D7-1))/12,0) | F7: =IF(C7="Operation",IF(D7<=PPATerm,PPAPrice,MerchantPrice)*(1+ColCPI/100)^(D7-1),0) | G7: =E7*F7*1000
A8: =Timeline_M!A8 | B8: =Timeline_M!B8 | C8: =Timeline_M!C8 | D8: =IF(C8="Operation",YEAR(A8)-YEAR(EDATE(StartDate,DevMonths+ConMonths))+1,0) | E8: =IF(C8="Operation",(P50MWh*(1-DegradPct/100)^(D8-1))/12,0) | F8: =IF(C8="Operation",IF(D8<=PPATerm,PPAPrice,MerchantPrice)*(1+ColCPI/100)^(D8-1),0) | G8: =E8*F8*1000
A9: =Timeline_M!A9 | B9: =Timeline_M!B9 | C9: =Timeline_M!C9 | D9: =IF(C9="Operation",YEAR(A9)-YEAR(EDATE(StartDate,DevMonths+ConMonths))+1,0) | E9: =IF(C9="Operation",(P50MWh*(1-DegradPct/100)^(D9-1))/12,0) | F9: =IF(C9="Operation",IF(D9<=PPATerm,PPAPrice,MerchantPrice)*(1+ColCPI/100)^(D9-1),0) | G9: =E9*F9*1000
A10: =Timeline_M!A10 | B10: =Timeline_M!B10 | C10: =Timeline_M!C10 | D10: =IF(C10="Operation",YEAR(A10)-YEAR(EDATE(StartDate,DevMonths+ConMonths))+1,0) | E10: =IF(C10="Operation",(P50MWh*(1-DegradPct/100)^(D10-1))/12,0) | F10: =IF(C10="Operation",IF(D10<=PPATerm,PPAPrice,MerchantPrice)*(1+ColCPI/100)^(D10-1),0) | G10: =E10*F10*1000
A11: =Timeline_M!A11 | B11: =Timeline_M!B11 | C11: =Timeline_M!C11 | D11: =IF(C11="Operation",YEAR(A11)-YEAR(EDATE(StartDate,DevMonths+ConMonths))+1,0) | E11: =IF(C11="Operation",(P50MWh*(1-DegradPct/100)^(D11-1))/12,0) | F11: =IF(C11="Operation",IF(D11<=PPATerm,PPAPrice,MerchantPrice)*(1+ColCPI/100)^(D11-1),0) | G11: =E11*F11*1000
A12: =Timeline_M!A12 | B12: =Timeline_M!B12 | C12: =Timeline_M!C12 | D12: =IF(C12="Operation",YEAR(A12)-YEAR(EDATE(StartDate,DevMonths+ConMonths))+1,0) | E12: =IF(C12="Operation",(P50MWh*(1-DegradPct/100)^(D12-1))/12,0) | F12: =IF(C12="Operation",IF(D12<=PPATerm,PPAPrice,MerchantPrice)*(1+ColCPI/100)^(D12-1),0) | G12: =E12*F12*1000
A13: =Timeline_M!A13 | B13: =Timeline_M!B13 | C13: =Timeline_M!C13 | D13: =IF(C13="Operation",YEAR(A13)-YEAR(EDATE(StartDate,DevMonths+ConMonths))+1,0) | E13: =IF(C13="Operation",(P50MWh*(1-DegradPct/100)^(D13-1))/12,0) | F13: =IF(C13="Operation",IF(D13<=PPATerm,PPAPrice,MerchantPrice)*(1+ColCPI/100)^(D13-1),0) | G13: =E13*F13*1000
... A500: =Timeline_M!A500 | B500: =Timeline_M!B500 | C500: =Timeline_M!C500 | D500: =IF(C500="Operation",YEAR(A500)-YEAR(EDATE(StartDate,DevMonths+ConMonths))+1,0) | E500: =IF(C500="Operation",(P50MWh*(1-DegradPct/100)^(D500-1))/12,0) | F500: =IF(C500="Operation",IF(D500<=PPATerm,PPAPrice,MerchantPrice)*(1+ColCPI/100)^(D500-1),0) | G500: =E500*F500*1000

Sheet OPEX_M
A1: Month | B1: Year | C1: Phase | D1: OperatingYear | E1: FixedOM | F1: VarOM | G1: Insurance | H1: GridFees | I1: OPEX_Total
A2: =Timeline_M!A2 | B2: =Timeline_M!B2 | C2: =Timeline_M!C2 | D2: =Revenue_M!D2 | E2: =IF(C2="Operation",(FixedOM*MWac*(1+ColCPI/100)^(D2-1))/12,0) | F2: =IF(C2="Operation",Revenue_M!E2*VarOM*(1+ColCPI/100)^(D2-1),0) | G2: =IF(C2="Operation",(Insurance*MWac*(1+ColCPI/100)^(D2-1))/12,0) | H2: =IF(C2="Operation",Revenue_M!E2*GridFees,0) | I2: =SUM(E2:H2)
A3: =Timeline_M!A3 | B3: =Timeline_M!B3 | C3: =Timeline_M!C3 | D3: =Revenue_M!D3 | E3: =IF(C3="Operation",(FixedOM*MWac*(1+ColCPI/100)^(D3-1))/12,0) | F3: =IF(C3="Operation",Revenue_M!E3*VarOM*(1+ColCPI/100)^(D3-1),0) | G3: =IF(C3="Operation",(Insurance*MWac*(1+ColCPI/100)^(D3-1))/12,0) | H3: =IF(C3="Operation",Revenue_M!E3*GridFees,0) | I3: =SUM(E3:H3)
A4: =Timeline_M!A4 | B4: =Timeline_M!B4 | C4: =Timeline_M!C4 | D4: =Revenue_M!D4 | E4: =IF(C4="Operation",(FixedOM*MWac*(1+ColCPI/100)^(D4-1))/12,0) | F4: =IF(C4="Operation",Revenue_M!E4*VarOM*(1+ColCPI/100)^(D4-1),0) | G4: =IF(C4="Operation",(Insurance*MWac*(1+ColCPI/100)^(D4-1))/12,0) | H4: =IF(C4="Operation",Revenue_M!E4*GridFees,0) | I4: =SUM(E4:H4)
A5: =Timeline_M!A5 | B5: =Timeline_M!B5 | C5: =Timeline_M!C5 | D5: =Revenue_M!D5 | E5: =IF(C5="Operation",(FixedOM*MWac*(1+ColCPI/100)^(D5-1))/12,0) | F5: =IF(C5="Operation",Revenue_M!E5*VarOM*(1+ColCPI/100)^(D5-1),0) | G5: =IF(C5="Operation",(Insurance*MWac*(1+ColCPI/100)^(D5-1))/12,0) | H5: =IF(C5="Operation",Revenue_M!E5*GridFees,0) | I5: =SUM(E5:H5)
A6: =Timeline_M!A6 | B6: =Timeline_M!B6 | C6: =Timeline_M!C6 | D6: =Revenue_M!D6 | E6: =IF(C6="Operation",(FixedOM*MWac*(1+ColCPI/100)^(D6-1))/12,0) | F6: =IF(C6="Operation",Revenue_M!E6*VarOM*(1+ColCPI/100)^(D6-1),0) | G6: =IF(C6="Operation",(Insurance*MWac*(1+ColCPI/100)^(D6-1))/12,0) | H6: =IF(C6="Operation",Revenue_M!E6*GridFees,0) | I6: =SUM(E6:H6)
A7: =Timeline_M!A7 | B7: =Timeline_M!B7 | C7: =Timeline_M!C7 | D7: =Revenue_M!D7 | E7: =IF(C7="Operation",(FixedOM*MWac*(1+ColCPI/100)^(D7-1))/12,0) | F7: =IF(C7="Operation",Revenue_M!E7*VarOM*(1+ColCPI/100)^(D7-1),0) | G7: =IF(C7="Operation",(Insurance*MWac*(1+ColCPI/100)^(D7-1))/12,0) | H7: =IF(C7="Operation",Revenue_M!E7*GridFees,0) | I7: =SUM(E7:H7)
A8: =Timeline_M!A8 | B8: =Timeline_M!B8 | C8: =Timeline_M!C8 | D8: =Revenue_M!D8 | E8: =IF(C8="Operation",(FixedOM*MWac*(1+ColCPI/100)^(D8-1))/12,0) | F8: =IF(C8="Operation",Revenue_M!E8*VarOM*(1+ColCPI/100)^(D8-1),0) | G8: =IF(C8="Operation",(Insurance*MWac*(1+ColCPI/100)^(D8-1))/12,0) | H8: =IF(C8="Operation",Revenue_M!E8*GridFees,0) | I8: =SUM(E8:H8)
A9: =Timeline_M!A9 | B9: =Timeline_M!B9 | C9: =Timeline_M!C9 | D9: =Revenue_M!D9 | E9: =IF(C9="Operation",(FixedOM*MWac*(1+ColCPI/100)^(D9-1))/12,0) | F9: =IF(C9="Operation",Revenue_M!E9*VarOM*(1+ColCPI/100)^(D9-1),0) | G9: =IF(C9="Operation",(Insurance*MWac*(1+ColCPI/100)^(D9-1))/12,0) | H9: =IF(C9="Operation",Revenue_M!E9*GridFees,0) | I9: =SUM(E9:H9)
A10: =Timeline_M!A10 | B10: =Timeline_M!B10 | C10: =Timeline_M!C10 | D10: =Revenue_M!D10 | E10: =IF(C10="Operation",(FixedOM*MWac*(1+ColCPI/100)^(D10-1))/12,0) | F10: =IF(C10="Operation",Revenue_M!E10*VarOM*(1+ColCPI/100)^(D10-1),0) | G10: =IF(C10="Operation",(Insurance*MWac*(1+ColCPI/100)^(D10-1))/12,0) | H10: =IF(C10="Operation",Revenue_M!E10*GridFees,0) | I10: =SUM(E10:H10)
A11: =Timeline_M!A11 | B11: =Timeline_M!B11 | C11: =Timeline_M!C11 | D11: =Revenue_M!D11 | E11: =IF(C11="Operation",(FixedOM*MWac*(1+ColCPI/100)^(D11-1))/12,0) | F11: =IF(C11="Operation",Revenue_M!E11*VarOM*(1+ColCPI/100)^(D11-1),0) | G11: =IF(C11="Operation",(Insurance*MWac*(1+ColCPI/100)^(D11-1))/12,0) | H11: =IF(C11="Operation",Revenue_M!E11*GridFees,0) | I11: =SUM(E11:H11)
A12: =Timeline_M!A12 | B12: =Timeline_M!B12 | C12: =Timeline_M!C12 | D12: =Revenue_M!D12 | E12: =IF(C12="Operation",(FixedOM*MWac*(1+ColCPI/100)^(D12-1))/12,0) | F12: =IF(C12="Operation",Revenue_M!E12*VarOM*(1+ColCPI/100)^(D12-1),0) | G12: =IF(C12="Operation",(Insurance*MWac*(1+ColCPI/100)^(D12-1))/12,0) | H12: =IF(C12="Operation",Revenue_M!E12*GridFees,0) | I12: =SUM(E12:H12)
A13: =Timeline_M!A13 | B13: =Timeline_M!B13 | C13: =Timeline_M!C13 | D13: =Revenue_M!D13 | E13: =IF(C13="Operation",(FixedOM*MWac*(1+ColCPI/100)^(D13-1))/12,0) | F13: =IF(C13="Operation",Revenue_M!E13*VarOM*(1+ColCPI/100)^(D13-1),0) | G13: =IF(C13="Operation",(Insurance*MWac*(1+ColCPI/100)^(D13-1))/12,0) | H13: =IF(C13="Operation",Revenue_M!E13*GridFees,0) | I13: =SUM(E13:H13)
... A500: =Timeline_M!A500 | B500: =Timeline_M!B500 | C500: =Timeline_M!C500 | D500: =Revenue_M!D500 | E500: =IF(C500="Operation",(FixedOM*MWac*(1+ColCPI/100)^(D500-1))/12,0) | F500: =IF(C500="Operation",Revenue_M!E500*VarOM*(1+ColCPI/100)^(D500-1),0) | G500: =IF(C500="Operation",(Insurance*MWac*(1+ColCPI/100)^(D500-1))/12,0) | H500: =IF(C500="Operation",Revenue_M!E500*GridFees,0) | I500: =SUM(E500:H500)

Sheet Debt_M
A1: Month | B1: Year | C1: Phase | D1: DebtDraw | E1: Interest | F1: Principal | G1: DebtService | H1: DebtFees | I1: DebtBalance | J1: TotalDebt | K1: MonthlyPrincipal | L1: CODMonth
A2: =Timeline_M!A2 | B2: =Timeline_M!B2 | C2: =Timeline_M!C2 | D2: =IF(AND(C2<>"Operation",DebtEnabled="Yes"),CAPEX_M!G2*DebtPct/100,0) | E2: =0 | F2: =0 | G2: =E2+F2 | H2: =0 | I2: =D2 | J2: =SUM(D:D) | K2: =IF(DebtEnabled="Yes",TotalDebt/(DebtTenor*12),0) | L2: =DevMonths+ConMonths+1
E3: =IF(AND(C3="Operation",DebtEnabled="Yes"),I2*DebtRate/100/12,0) | F3: =IF(AND(C3="Operation",DebtEnabled="Yes",Timeline_M!D3>=L2,Timeline_M!D3<L2+DebtTenor*12,I2>0),MIN(K2,I2),0) | G3: =E3+F3 | H3: =IF(AND(C3="Operation",Timeline_M!D3=L2,DebtEnabled="Yes"),TotalDebt*UpfrontFee/10000,0) | I3: =I2+D3-F3
A4: =Timeline_M!A4 | B4: =Timeline_M!B4 | C4: =Timeline_M!C4 | D4: =IF(AND(C4<>"Operation",DebtEnabled="Yes"),CAPEX_M!G4*DebtPct/100,0) | E4: =IF(AND(C4="Operation",DebtEnabled="Yes"),I3*DebtRate/100/12,0) | F4: =IF(AND(C4="Operation",DebtEnabled="Yes",Timeline_M!D4>=L2,Timeline_M!D4<L2+DebtTenor*12,I3>0),MIN(K2,I3),0) | G4: =E4+F4 | H4: =IF(AND(C4="Operation",Timeline_M!D4=L2,DebtEnabled="Yes"),TotalDebt*UpfrontFee/10000,0) | I4: =I3+D4-F4
A5: =Timeline_M!A5 | B5: =Timeline_M!B5 | C5: =Timeline_M!C5 | D5: =IF(AND(C5<>"Operation",DebtEnabled="Yes"),CAPEX_M!G5*DebtPct/100,0) | E5: =IF(AND(C5="Operation",DebtEnabled="Yes"),I4*DebtRate/100/12,0) | F5: =IF(AND(C5="Operation",DebtEnabled="Yes",Timeline_M!D5>=L2,Timeline_M!D5<L2+DebtTenor*12,I4>0),MIN(K2,I4),0) | G5: =E5+F5 | H5: =IF(AND(C5="Operation",Timeline_M!D5=L2,DebtEnabled="Yes"),TotalDebt*UpfrontFee/10000,0) | I5: =I4+D5-F5
A6: =Timeline_M!A6 | B6: =Timeline_M!B6 | C6: =Timeline_M!C6 | D6: =IF(AND(C6<>"Operation",DebtEnabled="Yes"),CAPEX_M!G6*DebtPct/100,0) | E6: =IF(AND(C6="Operation",DebtEnabled="Yes"),I5*DebtRate/100/12,0) | F6: =IF(AND(C6="Operation",DebtEnabled="Yes",Timeline_M!D6>=L2,Timeline_M!D6<L2+DebtTenor*12,I5>0),MIN(K2,I5),0) | G6: =E6+F6 | H6: =IF(AND(C6="Operation",Timeline_M!D6=L2,DebtEnabled="Yes"),TotalDebt*UpfrontFee/10000,0) | I6: =I5+D6-F6
A7: =Timeline_M!A7 | B7: =Timeline_M!B7 | C7: =Timeline_M!C7 | D7: =IF(AND(C7<>"Operation",DebtEnabled="Yes"),CAPEX_M!G7*DebtPct/100,0) | E7: =IF(AND(C7="Operation",DebtEnabled="Yes"),I6*DebtRate/100/12,0) | F7: =IF(AND(C7="Operation",DebtEnabled="Yes",Timeline_M!D7>=L2,Timeline_M!D7<L2+DebtTenor*12,I6>0),MIN(K2,I6),0) | G7: =E7+F7 | H7: =IF(AND(C7="Operation",Timeline_M!D7=L2,DebtEnabled="Yes"),TotalDebt*UpfrontFee/10000,0) | I7: =I6+D7-F7
A8: =Timeline_M!A8 | B8: =Timeline_M!B8 | C8: =Timeline_M!C8 | D8: =IF(AND(C8<>"Operation",DebtEnabled="Yes"),CAPEX_M!G8*DebtPct/100,0) | E8: =IF(AND(C8="Operation",DebtEnabled="Yes"),I7*DebtRate/100/12,0) | F8: =IF(AND(C8="Operation",DebtEnabled="Yes",Timeline_M!D8>=L2,Timeline_M!D8<L2+DebtTenor*12,I7>0),MIN(K2,I7),0) | G8: =E8+F8 | H8: =IF(AND(C8="Operation",Timeline_M!D8=L2,DebtEnabled="Yes"),TotalDebt*UpfrontFee/10000,0) | I8: =I7+D8-F8
A9: =Timeline_M!A9 | B9: =Timeline_M!B9 | C9: =Timeline_M!C9 | D9: =IF(AND(C9<>"Operation",DebtEnabled="Yes"),CAPEX_M!G9*DebtPct/100,0) | E9: =IF(AND(C9="Operation",DebtEnabled="Yes"),I8*DebtRate/100/12,0) | F9: =IF(AND(C9="Operation",DebtEnabled="Yes",Timeline_M!D9>=L2,Timeline_M!D9<L2+DebtTenor*12,I8>0),MIN(K2,I8),0) | G9: =E9+F9 | H9: =IF(AND(C9="Operation",Timeline_M!D9=L2,DebtEnabled="Yes"),TotalDebt*UpfrontFee/10000,0) | I9: =I8+D9-F9
A10: =Timeline_M!A10 | B10: =Timeline_M!B10 | C10: =Timeline_M!C10 | D10: =IF(AND(C10<>"Operation",DebtEnabled="Yes"),CAPEX_M!G10*DebtPct/100,0) | E10: =IF(AND(C10="Operation",DebtEnabled="Yes"),I9*DebtRate/100/12,0) | F10: =IF(AND(C10="Operation",DebtEnabled="Yes",Timeline_M!D10>=L2,Timeline_M!D10<L2+DebtTenor*12,I9>0),MIN(K2,I9),0) | G10: =E10+F10 | H10: =IF(AND(C10="Operation",Timeline_M!D10=L2,DebtEnabled="Yes"),TotalDebt*UpfrontFee/10000,0) | I10: =I9+D10-F10
A11: =Timeline_M!A11 | B11: =Timeline_M!B11 | C11: =Timeline_M!C11 | D11: =IF(AND(C11<>"Operation",DebtEnabled="Yes"),CAPEX_M!G11*DebtPct/100,0) | E11: =IF(AND(C11="Operation",DebtEnabled="Yes"),I10*DebtRate/100/12,0) | F11: =IF(AND(C11="Operation",DebtEnabled="Yes",Timeline_M!D11>=L2,Timeline_M!D11<L2+DebtTenor*12,I10>0),MIN(K2,I10),0) | G11: =E11+F11 | H11: =IF(AND(C11="Operation",Timeline_M!D11=L2,DebtEnabled="Yes"),TotalDebt*UpfrontFee/10000,0) | I11: =I10+D11-F11
A12: =Timeline_M!A12 | B12: =Timeline_M!B12 | C12: =Timeline_M!C12 | D12: =IF(AND(C12<>"Operation",DebtEnabled="Yes"),CAPEX_M!G12*DebtPct/100,0) | E12: =IF(AND(C12="Operation",DebtEnabled="Yes"),I11*DebtRate/100/12,0) | F12: =IF(AND(C12="Operation",DebtEnabled="Yes",Timeline_M!D12>=L2,Timeline_M!D12<L2+DebtTenor*12,I11>0),MIN(K2,I11),0) | G12: =E12+F12 | H12: =IF(AND(C12="Operation",Timeline_M!D12=L2,DebtEnabled="Yes"),TotalDebt*UpfrontFee/10000,0) | I12: =I11+D12-F12
A13: =Timeline_M!A13 | B13: =Timeline_M!B13 | C13: =Timeline_M!C13 | D13: =IF(AND(C13<>"Operation",DebtEnabled="Yes"),CAPEX_M!G13*DebtPct/100,0) | E13: =IF(AND(C13="Operation",DebtEnabled="Yes"),I12*DebtRate/100/12,0) | F13: =IF(AND(C13="Operation",DebtEnabled="Yes",Timeline_M!D13>=L2,Timeline_M!D13<L2+DebtTenor*12,I12>0),MIN(K2,I12),0) | G13: =E13+F13 | H13: =IF(AND(C13="Operation",Timeline_M!D13=L2,DebtEnabled="Yes"),TotalDebt*UpfrontFee/10000,0) | I13: =I12+D13-F13
A14: =Timeline_M!A14 | B14: =Timeline_M!B14 | C14: =Timeline_M!C14 | D14: =IF(AND(C14<>"Operation",DebtEnabled="Yes"),CAPEX_M!G14*DebtPct/100,0) | E14: =IF(AND(C14="Operation",DebtEnabled="Yes"),I13*DebtRate/100/12,0) | F14: =IF(AND(C14="Operation",DebtEnabled="Yes",Timeline_M!D14>=L2,Timeline_M!D14<L2+DebtTenor*12,I13>0),MIN(K2,I13),0) | G14: =E14+F14 | H14: =IF(AND(C14="Operation",Timeline_M!D14=L2,DebtEnabled="Yes"),TotalDebt*UpfrontFee/10000,0) | I14: =I13+D14-F14
A15: =Timeline_M!A15 | B15: =Timeline_M!B15 | C15: =Timeline_M!C15 | D15: =IF(AND(C15<>"Operation",DebtEnabled="Yes"),CAPEX_M!G15*DebtPct/100,0) | E15: =IF(AND(C15="Operation",DebtEnabled="Yes"),I14*DebtRate/100/12,0) | F15: =IF(AND(C15="Operation",DebtEnabled="Yes",Timeline_M!D15>=L2,Timeline_M!D15<L2+DebtTenor*12,I14>0),MIN(K2,I14),0) | G15: =E15+F15 | H15: =IF(AND(C15="Operation",Timeline_M!D15=L2,DebtEnabled="Yes"),TotalDebt*UpfrontFee/10000,0) | I15: =I14+D15-F15
A16: =Timeline_M!A16 | B16: =Timeline_M!B16 | C16: =Timeline_M!C16 | D16: =IF(AND(C16<>"Operation",DebtEnabled="Yes"),CAPEX_M!G16*DebtPct/100,0) | E16: =IF(AND(C16="Operation",DebtEnabled="Yes"),I15*DebtRate/100/12,0) | F16: =IF(AND(C16="Operation",DebtEnabled="Yes",Timeline_M!D16>=L2,Timeline_M!D16<L2+DebtTenor*12,I15>0),MIN(K2,I15),0) | G16: =E16+F16 | H16: =IF(AND(C16="Operation",Timeline_M!D16=L2,DebtEnabled="Yes"),TotalDebt*UpfrontFee/10000,0) | I16: =I15+D16-F16
A17: =Timeline_M!A17 | B17: =Timeline_M!B17 | C17: =Timeline_M!C17 | D17: =IF(AND(C17<>"Operation",DebtEnabled="Yes"),CAPEX_M!G17*DebtPct/100,0) | E17: =IF(AND(C17="Operation",DebtEnabled="Yes"),I16*DebtRate/100/12,0) | F17: =IF(AND(C17="Operation",DebtEnabled="Yes",Timeline_M!D17>=L2,Timeline_M!D17<L2+DebtTenor*12,I16>0),MIN(K2,I16),0) | G17: =E17+F17 | H17: =IF(AND(C17="Operation",Timeline_M!D17=L2,DebtEnabled="Yes"),TotalDebt*UpfrontFee/10000,0) | I17: =I16+D17-F17
A18: =Timeline_M!A18 | B18: =Timeline_M!B18 | C18: =Timeline_M!C18 | D18: =IF(AND(C18<>"Operation",DebtEnabled="Yes"),CAPEX_M!G18*DebtPct/100,0) | E18: =IF(AND(C18="Operation",DebtEnabled="Yes"),I17*DebtRate/100/12,0) | F18: =IF(AND(C18="Operation",DebtEnabled="Yes",Timeline_M!D18>=L2,Timeline_M!D18<L2+DebtTenor*12,I17>0),MIN(K2,I17),0) | G18: =E18+F18 | H18: =IF(AND(C18="Operation",Timeline_M!D18=L2,DebtEnabled="Yes"),TotalDebt*UpfrontFee/10000,0) | I18: =I17+D18-F18
A19: =Timeline_M!A19 | B19: =Timeline_M!B19 | C19: =Timeline_M!C19 | D19: =IF(AND(C19<>"Operation",DebtEnabled="Yes"),CAPEX_M!G19*DebtPct/100,0) | E19: =IF(AND(C19="Operation",DebtEnabled="Yes"),I18*DebtRate/100/12,0) | F19: =IF(AND(C19="Operation",DebtEnabled="Yes",Timeline_M!D19>=L2,Timeline_M!D19<L2+DebtTenor*12,I18>0),MIN(K2,I18),0) | G19: =E19+F19 | H19: =IF(AND(C19="Operation",Timeline_M!D19=L2,DebtEnabled="Yes"),TotalDebt*UpfrontFee/10000,0) | I19: =I18+D19-F19
A20: =Timeline_M!A20 | B20: =Timeline_M!B20 | C20: =Timeline_M!C20 | D20: =IF(AND(C20<>"Operation",DebtEnabled="Yes"),CAPEX_M!G20*DebtPct/100,0) | E20: =IF(AND(C20="Operation",DebtEnabled="Yes"),I19*DebtRate/100/12,0) | F20: =IF(AND(C20="Operation",DebtEnabled="Yes",Timeline_M!D20>=L2,Timeline_M!D20<L2+DebtTenor*12,I19>0),MIN(K2,I19),0) | G20: =E20+F20 | H20: =IF(AND(C20="Operation",Timeline_M!D20=L2,DebtEnabled="Yes"),TotalDebt*UpfrontFee/10000,0) | I20: =I19+D20-F20
A21: =Timeline_M!A21 | B21: =Timeline_M!B21 | C21: =Timeline_M!C21 | D21: =IF(AND(C21<>"Operation",DebtEnabled="Yes"),CAPEX_M!G21*DebtPct/100,0) | E21: =IF(AND(C21="Operation",DebtEnabled="Yes"),I20*DebtRate/100/12,0) | F21: =IF(AND(C21="Operation",DebtEnabled="Yes",Timeline_M!D21>=L2,Timeline_M!D21<L2+DebtTenor*12,I20>0),MIN(K2,I20),0) | G21: =E21+F21 | H21: =IF(AND(C21="Operation",Timeline_M!D21=L2,DebtEnabled="Yes"),TotalDebt*UpfrontFee/10000,0) | I21: =I20+D21-F21
A22: =Timeline_M!A22 | B22: =Timeline_M!B22 | C22: =Timeline_M!C22 | D22: =IF(AND(C22<>"Operation",DebtEnabled="Yes"),CAPEX_M!G22*DebtPct/100,0) | E22: =IF(AND(C22="Operation",DebtEnabled="Yes"),I21*DebtRate/100/12,0) | F22: =IF(AND(C22="Operation",DebtEnabled="Yes",Timeline_M!D22>=L2,Timeline_M!D22<L2+DebtTenor*12,I21>0),MIN(K2,I21),0) | G22: =E22+F22 | H22: =IF(AND(C22="Operation",Timeline_M!D22=L2,DebtEnabled="Yes"),TotalDebt*UpfrontFee/10000,0) | I22: =I21+D22-F22
A23: =Timeline_M!A23 | B23: =Timeline_M!B23 | C23: =Timeline_M!C23 | D23: =IF(AND(C23<>"Operation",DebtEnabled="Yes"),CAPEX_M!G23*DebtPct/100,0) | E23: =IF(AND(C23="Operation",DebtEnabled="Yes"),I22*DebtRate/100/12,0) | F23: =IF(AND(C23="Operation",DebtEnabled="Yes",Timeline_M!D23>=L2,Timeline_M!D23<L2+DebtTenor*12,I22>0),MIN(K2,I22),0) | G23: =E23+F23 | H23: =IF(AND(C23="Operation",Timeline_M!D23=L2,DebtEnabled="Yes"),TotalDebt*UpfrontFee/10000,0) | I23: =I22+D23-F23
A24: =Timeline_M!A24 | B24: =Timeline_M!B24 | C24: =Timeline_M!C24 | D24: =IF(AND(C24<>"Operation",DebtEnabled="Yes"),CAPEX_M!G24*DebtPct/100,0) | E24: =IF(AND(C24="Operation",DebtEnabled="Yes"),I23*DebtRate/100/12,0) | F24: =IF(AND(C24="Operation",DebtEnabled="Yes",Timeline_M!D24>=L2,Timeline_M!D24<L2+DebtTenor*12,I23>0),MIN(K2,I23),0) | G24: =E24+F24 | H24: =IF(AND(C24="Operation",Timeline_M!D24=L2,DebtEnabled="Yes"),TotalDebt*UpfrontFee/10000,0) | I24: =I23+D24-F24
A25: =Timeline_M!A25 | B25: =Timeline_M!B25 | C25: =Timeline_M!C25 | D25: =IF(AND(C25<>"Operation",DebtEnabled="Yes"),CAPEX_M!G25*DebtPct/100,0) | E25: =IF(AND(C25="Operation",DebtEnabled="Yes"),I24*DebtRate/100/12,0) | F25: =IF(AND(C25="Operation",DebtEnabled="Yes",Timeline_M!D25>=L2,Timeline_M!D25<L2+DebtTenor*12,I24>0),MIN(K2,I24),0) | G25: =E25+F25 | H25: =IF(AND(C25="Operation",Timeline_M!D25=L2,DebtEnabled="Yes"),TotalDebt*UpfrontFee/10000,0) | I25: =I24+D25-F25
A26: =Timeline_M!A26 | B26: =Timeline_M!B26 | C26: =Timeline_M!C26 | D26: =IF(AND(C26<>"Operation",DebtEnabled="Yes"),CAPEX_M!G26*DebtPct/100,0) | E26: =IF(AND(C26="Operation",DebtEnabled="Yes"),I25*DebtRate/100/12,0) | F26: =IF(AND(C26="Operation",DebtEnabled="Yes",Timeline_M!D26>=L2,Timeline_M!D26<L2+DebtTenor*12,I25>0),MIN(K2,I25),0) | G26: =E26+F26 | H26: =IF(AND(C26="Operation",Timeline_M!D26=L2,DebtEnabled="Yes"),TotalDebt*UpfrontFee/10000,0) | I26: =I25+D26-F26
A27: =Timeline_M!A27 | B27: =Timeline_M!B27 | C27: =Timeline_M!C27 | D27: =IF(AND(C27<>"Operation",DebtEnabled="Yes"),CAPEX_M!G27*DebtPct/100,0) | E27: =IF(AND(C27="Operation",DebtEnabled="Yes"),I26*DebtRate/100/12,0) | F27: =IF(AND(C27="Operation",DebtEnabled="Yes",Timeline_M!D27>=L2,Timeline_M!D27<L2+DebtTenor*12,I26>0),MIN(K2,I26),0) | G27: =E27+F27 | H27: =IF(AND(C27="Operation",Timeline_M!D27=L2,DebtEnabled="Yes"),TotalDebt*UpfrontFee/10000,0) | I27: =I26+D27-F27
A28: =Timeline_M!A28 | B28: =Timeline_M!B28 | C28: =Timeline_M!C28 | D28: =IF(AND(C28<>"Operation",DebtEnabled="Yes"),CAPEX_M!G28*DebtPct/100,0) | E28: =IF(AND(C28="Operation",DebtEnabled="Yes"),I27*DebtRate/100/12,0) | F28: =IF(AND(C28="Operation",DebtEnabled="Yes",Timeline_M!D28>=L2,Timeline_M!D28<L2+DebtTenor*12,I27>0),MIN(K2,I27),0) | G28: =E28+F28 | H28: =IF(AND(C28="Operation",Timeline_M!D28=L2,DebtEnabled="Yes"),TotalDebt*UpfrontFee/10000,0) | I28: =I27+D28-F28
A29: =Timeline_M!A29 | B29: =Timeline_M!B29 | C29: =Timeline_M!C29 | D29: =IF(AND(C29<>"Operation",DebtEnabled="Yes"),CAPEX_M!G29*DebtPct/100,0) | E29: =IF(AND(C29="Operation",DebtEnabled="Yes"),I28*DebtRate/100/12,0) | F29: =IF(AND(C29="Operation",DebtEnabled="Yes",Timeline_M!D29>=L2,Timeline_M!D29<L2+DebtTenor*12,I28>0),MIN(K2,I28),0) | G29: =E29+F29 | H29: =IF(AND(C29="Operation",Timeline_M!D29=L2,DebtEnabled="Yes"),TotalDebt*UpfrontFee/10000,0) | I29: =I28+D29-F29
A30: =Timeline_M!A30 | B30: =Timeline_M!B30 | C30: =Timeline_M!C30 | D30: =IF(AND(C30<>"Operation",DebtEnabled="Yes"),CAPEX_M!G30*DebtPct/100,0) | E30: =IF(AND(C30="Operation",DebtEnabled="Yes"),I29*DebtRate/100/12,0) | F30: =IF(AND(C30="Operation",DebtEnabled="Yes",Timeline_M!D30>=L2,Timeline_M!D30<L2+DebtTenor*12,I29>0),MIN(K2,I29),0) | G30: =E30+F30 | H30: =IF(AND(C30="Operation",Timeline_M!D30=L2,DebtEnabled="Yes"),TotalDebt*UpfrontFee/10000,0) | I30: =I29+D30-F30
A31: =Timeline_M!A31 | B31: =Timeline_M!B31 | C31: =Timeline_M!C31 | D31: =IF(AND(C31<>"Operation",DebtEnabled="Yes"),CAPEX_M!G31*DebtPct/100,0) | E31: =IF(AND(C31="Operation",DebtEnabled="Yes"),I30*DebtRate/100/12,0) | F31: =IF(AND(C31="Operation",DebtEnabled="Yes",Timeline_M!D31>=L2,Timeline_M!D31<L2+DebtTenor*12,I30>0),MIN(K2,I30),0) | G31: =E31+F31 | H31: =IF(AND(C31="Operation",Timeline_M!D31=L2,DebtEnabled="Yes"),TotalDebt*UpfrontFee/10000,0) | I31: =I30+D31-F31
A32: =Timeline_M!A32 | B32: =Timeline_M!B32 | C32: =Timeline_M!C32 | D32: =IF(AND(C32<>"Operation",DebtEnabled="Yes"),CAPEX_M!G32*DebtPct/100,0) | E32: =IF(AND(C32="Operation",DebtEnabled="Yes"),I31*DebtRate/100/12,0) | F32: =IF(AND(C32="Operation",DebtEnabled="Yes",Timeline_M!D32>=L2,Timeline_M!D32<L2+DebtTenor*12,I31>0),MIN(K2,I31),0) | G32: =E32+F32 | H32: =IF(AND(C32="Operation",Timeline_M!D32=L2,DebtEnabled="Yes"),TotalDebt*UpfrontFee/10000,0) | I32: =I31+D32-F32
A33: =Timeline_M!A33 | B33: =Timeline_M!B33 | C33: =Timeline_M!C33 | D33: =IF(AND(C33<>"Operation",DebtEnabled="Yes"),CAPEX_M!G33*DebtPct/100,0) | E33: =IF(AND(C33="Operation",DebtEnabled="Yes"),I32*DebtRate/100/12,0) | F33: =IF(AND(C33="Operation",DebtEnabled="Yes",Timeline_M!D33>=L2,Timeline_M!D33<L2+DebtTenor*12,I32>0),MIN(K2,I32),0) | G33: =E33+F33 | H33: =IF(AND(C33="Operation",Timeline_M!D33=L2,DebtEnabled="Yes"),TotalDebt*UpfrontFee/10000,0) | I33: =I32+D33-F33
A34: =Timeline_M!A34 | B34: =Timeline_M!B34 | C34: =Timeline_M!C34 | D34: =IF(AND(C34<>"Operation",DebtEnabled="Yes"),CAPEX_M!G34*DebtPct/100,0) | E34: =IF(AND(C34="Operation",DebtEnabled="Yes"),I33*DebtRate/100/12,0) | F34: =IF(AND(C34="Operation",DebtEnabled="Yes",Timeline_M!D34>=L2,Timeline_M!D34<L2+DebtTenor*12,I33>0),MIN(K2,I33),0) | G34: =E34+F34 | H34: =IF(AND(C34="Operation",Timeline_M!D34=L2,DebtEnabled="Yes"),TotalDebt*UpfrontFee/10000,0) | I34: =I33+D34-F34
A35: =Timeline_M!A35 | B35: =Timeline_M!B35 | C35: =Timeline_M!C35 | D35: =IF(AND(C35<>"Operation",DebtEnabled="Yes"),CAPEX_M!G35*DebtPct/100,0) | E35: =IF(AND(C35="Operation",DebtEnabled="Yes"),I34*DebtRate/100/12,0) | F35: =IF(AND(C35="Operation",DebtEnabled="Yes",Timeline_M!D35>=L2,Timeline_M!D35<L2+DebtTenor*12,I34>0),MIN(K2,I34),0) | G35: =E35+F35 | H35: =IF(AND(C35="Operation",Timeline_M!D35=L2,DebtEnabled="Yes"),TotalDebt*UpfrontFee/10000,0) | I35: =I34+D35-F35
A36: =Timeline_M!A36 | B36: =Timeline_M!B36 | C36: =Timeline_M!C36 | D36: =IF(AND(C36<>"Operation",DebtEnabled="Yes"),CAPEX_M!G36*DebtPct/100,0) | E36: =IF(AND(C36="Operation",DebtEnabled="Yes"),I35*DebtRate/100/12,0) | F36: =IF(AND(C36="Operation",DebtEnabled="Yes",Timeline_M!D36>=L2,Timeline_M!D36<L2+DebtTenor*12,I35>0),MIN(K2,I35),0) | G36: =E36+F36 | H36: =IF(AND(C36="Operation",Timeline_M!D36=L2,DebtEnabled="Yes"),TotalDebt*UpfrontFee/10000,0) | I36: =I35+D36-F36
A37: =Timeline_M!A37 | B37: =Timeline_M!B37 | C37: =Timeline_M!C37 | D37: =IF(AND(C37<>"Operation",DebtEnabled="Yes"),CAPEX_M!G37*DebtPct/100,0) | E37: =IF(AND(C37="Operation",DebtEnabled="Yes"),I36*DebtRate/100/12,0) | F37: =IF(AND(C37="Operation",DebtEnabled="Yes",Timeline_M!D37>=L2,Timeline_M!D37<L2+DebtTenor*12,I36>0),MIN(K2,I36),0) | G37: =E37+F37 | H37: =IF(AND(C37="Operation",Timeline_M!D37=L2,DebtEnabled="Yes"),TotalDebt*UpfrontFee/10000,0) | I37: =I36+D37-F37
A38: =Timeline_M!A38 | B38: =Timeline_M!B38 | C38: =Timeline_M!C38 | D38: =IF(AND(C38<>"Operation",DebtEnabled="Yes"),CAPEX_M!G38*DebtPct/100,0) | E38: =IF(AND(C38="Operation",DebtEnabled="Yes"),I37*DebtRate/100/12,0) | F38: =IF(AND(C38="Operation",DebtEnabled="Yes",Timeline_M!D38>=L2,Timeline_M!D38<L2+DebtTenor*12,I37>0),MIN(K2,I37),0) | G38: =E38+F38 | H38: =IF(AND(C38="Operation",Timeline_M!D38=L2,DebtEnabled="Yes"),TotalDebt*UpfrontFee/10000,0) | I38: =I37+D38-F38
A39: =Timeline_M!A39 | B39: =Timeline_M!B39 | C39: =Timeline_M!C39 | D39: =IF(AND(C39<>"Operation",DebtEnabled="Yes"),CAPEX_M!G39*DebtPct/100,0) | E39: =IF(AND(C39="Operation",DebtEnabled="Yes"),I38*DebtRate/100/12,0) | F39: =IF(AND(C39="Operation",DebtEnabled="Yes",Timeline_M!D39>=L2,Timeline_M!D39<L2+DebtTenor*12,I38>0),MIN(K2,I38),0) | G39: =E39+F39 | H39: =IF(AND(C39="Operation",Timeline_M!D39=L2,DebtEnabled="Yes"),TotalDebt*UpfrontFee/10000,0) | I39: =I38+D39-F39
A40: =Timeline_M!A40 | B40: =Timeline_M!B40 | C40: =Timeline_M!C40 | D40: =IF(AND(C40<>"Operation",DebtEnabled="Yes"),CAPEX_M!G40*DebtPct/100,0) | E40: =IF(AND(C40="Operation",DebtEnabled="Yes"),I39*DebtRate/100/12,0) | F40: =IF(AND(C40="Operation",DebtEnabled="Yes",Timeline_M!D40>=L2,Timeline_M!D40<L2+DebtTenor*12,I39>0),MIN(K2,I39),0) | G40: =E40+F40 | H40: =IF(AND(C40="Operation",Timeline_M!D40=L2,DebtEnabled="Yes"),TotalDebt*UpfrontFee/10000,0) | I40: =I39+D40-F40
A41: =Timeline_M!A41 | B41: =Timeline_M!B41 | C41: =Timeline_M!C41 | D41: =IF(AND(C41<>"Operation",DebtEnabled="Yes"),CAPEX_M!G41*DebtPct/100,0) | E41: =IF(AND(C41="Operation",DebtEnabled="Yes"),I40*DebtRate/100/12,0) | F41: =IF(AND(C41="Operation",DebtEnabled="Yes",Timeline_M!D41>=L2,Timeline_M!D41<L2+DebtTenor*12,I40>0),MIN(K2,I40),0) | G41: =E41+F41 | H41: =IF(AND(C41="Operation",Timeline_M!D41=L2,DebtEnabled="Yes"),TotalDebt*UpfrontFee/10000,0) | I41: =I40+D41-F41
A42: =Timeline_M!A42 | B42: =Timeline_M!B42 | C42: =Timeline_M!C42 | D42: =IF(AND(C42<>"Operation",DebtEnabled="Yes"),CAPEX_M!G42*DebtPct/100,0) | E42: =IF(AND(C42="Operation",DebtEnabled="Yes"),I41*DebtRate/100/12,0) | F42: =IF(AND(C42="Operation",DebtEnabled="Yes",Timeline_M!D42>=L2,Timeline_M!D42<L2+DebtTenor*12,I41>0),MIN(K2,I41),0) | G42: =E42+F42 | H42: =IF(AND(C42="Operation",Timeline_M!D42=L2,DebtEnabled="Yes"),TotalDebt*UpfrontFee/10000,0) | I42: =I41+D42-F42
A43: =Timeline_M!A43 | B43: =Timeline_M!B43 | C43: =Timeline_M!C43 | D43: =IF(AND(C43<>"Operation",DebtEnabled="Yes"),CAPEX_M!G43*DebtPct/100,0) | E43: =IF(AND(C43="Operation",DebtEnabled="Yes"),I42*DebtRate/100/12,0) | F43: =IF(AND(C43="Operation",DebtEnabled="Yes",Timeline_M!D43>=L2,Timeline_M!D43<L2+DebtTenor*12,I42>0),MIN(K2,I42),0) | G43: =E43+F43 | H43: =IF(AND(C43="Operation",Timeline_M!D43=L2,DebtEnabled="Yes"),TotalDebt*UpfrontFee/10000,0) | I43: =I42+D43-F43
A44: =Timeline_M!A44 | B44: =Timeline_M!B44 | C44: =Timeline_M!C44 | D44: =IF(AND(C44<>"Operation",DebtEnabled="Yes"),CAPEX_M!G44*DebtPct/100,0) | E44: =IF(AND(C44="Operation",DebtEnabled="Yes"),I43*DebtRate/100/12,0) | F44: =IF(AND(C44="Operation",DebtEnabled="Yes",Timeline_M!D44>=L2,Timeline_M!D44<L2+DebtTenor*12,I43>0),MIN(K2,I43),0) | G44: =E44+F44 | H44: =IF(AND(C44="Operation",Timeline_M!D44=L2,DebtEnabled="Yes"),TotalDebt*UpfrontFee/10000,0) | I44: =I43+D44-F44
A45: =Timeline_M!A45 | B45: =Timeline_M!B45 | C45: =Timeline_M!C45 | D45: =IF(AND(C45<>"Operation",DebtEnabled="Yes"),CAPEX_M!G45*DebtPct/100,0) | E45: =IF(AND(C45="Operation",DebtEnabled="Yes"),I44*DebtRate/100/12,0) | F45: =IF(AND(C45="Operation",DebtEnabled="Yes",Timeline_M!D45>=L2,Timeline_M!D45<L2+DebtTenor*12,I44>0),MIN(K2,I44),0) | G45: =E45+F45 | H45: =IF(AND(C45="Operation",Timeline_M!D45=L2,DebtEnabled="Yes"),TotalDebt*UpfrontFee/10000,0) | I45: =I44+D45-F45
A46: =Timeline_M!A46 | B46: =Timeline_M!B46 | C46: =Timeline_M!C46 | D46: =IF(AND(C46<>"Operation",DebtEnabled="Yes"),CAPEX_M!G46*DebtPct/100,0) | E46: =IF(AND(C46="Operation",DebtEnabled="Yes"),I45*DebtRate/100/12,0) | F46: =IF(AND(C46="Operation",DebtEnabled="Yes",Timeline_M!D46>=L2,Timeline_M!D46<L2+DebtTenor*12,I45>0),MIN(K2,I45),0) | G46: =E46+F46 | H46: =IF(AND(C46="Operation",Timeline_M!D46=L2,DebtEnabled="Yes"),TotalDebt*UpfrontFee/10000,0) | I46: =I45+D46-F46
A47: =Timeline_M!A47 | B47: =Timeline_M!B47 | C47: =Timeline_M!C47 | D47: =IF(AND(C47<>"Operation",DebtEnabled="Yes"),CAPEX_M!G47*DebtPct/100,0) | E47: =IF(AND(C47="Operation",DebtEnabled="Yes"),I46*DebtRate/100/12,0) | F47: =IF(AND(C47="Operation",DebtEnabled="Yes",Timeline_M!D47>=L2,Timeline_M!D47<L2+DebtTenor*12,I46>0),MIN(K2,I46),0) | G47: =E47+F47 | H47: =IF(AND(C47="Operation",Timeline_M!D47=L2,DebtEnabled="Yes"),TotalDebt*UpfrontFee/10000,0) | I47: =I46+D47-F47
A48: =Timeline_M!A48 | B48: =Timeline_M!B48 | C48: =Timeline_M!C48 | D48: =IF(AND(C48<>"Operation",DebtEnabled="Yes"),CAPEX_M!G48*DebtPct/100,0) | E48: =IF(AND(C48="Operation",DebtEnabled="Yes"),I47*DebtRate/100/12,0) | F48: =IF(AND(C48="Operation",DebtEnabled="Yes",Timeline_M!D48>=L2,Timeline_M!D48<L2+DebtTenor*12,I47>0),MIN(K2,I47),0) | G48: =E48+F48 | H48: =IF(AND(C48="Operation",Timeline_M!D48=L2,DebtEnabled="Yes"),TotalDebt*UpfrontFee/10000,0) | I48: =I47+D48-F48
A49: =Timeline_M!A49 | B49: =Timeline_M!B49 | C49: =Timeline_M!C49 | D49: =IF(AND(C49<>"Operation",DebtEnabled="Yes"),CAPEX_M!G49*DebtPct/100,0) | E49: =IF(AND(C49="Operation",DebtEnabled="Yes"),I48*DebtRate/100/12,0) | F49: =IF(AND(C49="Operation",DebtEnabled="Yes",Timeline_M!D49>=L2,Timeline_M!D49<L2+DebtTenor*12,I48>0),MIN(K2,I48),0) | G49: =E49+F49 | H49: =IF(AND(C49="Operation",Timeline_M!D49=L2,DebtEnabled="Yes"),TotalDebt*UpfrontFee/10000,0) | I49: =I48+D49-F49
A50: =Timeline_M!A50 | B50: =Timeline_M!B50 | C50: =Timeline_M!C50 | D50: =IF(AND(C50<>"Operation",DebtEnabled="Yes"),CAPEX_M!G50*DebtPct/100,0) | E50: =IF(AND(C50="Operation",DebtEnabled="Yes"),I49*DebtRate/100/12,0) | F50: =IF(AND(C50="Operation",DebtEnabled="Yes",Timeline_M!D50>=L2,Timeline_M!D50<L2+DebtTenor*12,I49>0),MIN(K2,I49),0) | G50: =E50+F50 | H50: =IF(AND(C50="Operation",Timeline_M!D50=L2,DebtEnabled="Yes"),TotalDebt*UpfrontFee/10000,0) | I50: =I49+D50-F50
A51: =Timeline_M!A51 | B51: =Timeline_M!B51 | C51: =Timeline_M!C51 | D51: =IF(AND(C51<>"Operation",DebtEnabled="Yes"),CAPEX_M!G51*DebtPct/100,0) | E51: =IF(AND(C51="Operation",DebtEnabled="Yes"),I50*DebtRate/100/12,0) | F51: =IF(AND(C51="Operation",DebtEnabled="Yes",Timeline_M!D51>=L2,Timeline_M!D51<L2+DebtTenor*12,I50>0),MIN(K2,I50),0) | G51: =E51+F51 | H51: =IF(AND(C51="Operation",Timeline_M!D51=L2,DebtEnabled="Yes"),TotalDebt*UpfrontFee/10000,0) | I51: =I50+D51-F51
A52: =Timeline_M!A52 | B52: =Timeline_M!B52 | C52: =Timeline_M!C52 | D52: =IF(AND(C52<>"Operation",DebtEnabled="Yes"),CAPEX_M!G52*DebtPct/100,0) | E52: =IF(AND(C52="Operation",DebtEnabled="Yes"),I51*DebtRate/100/12,0) | F52: =IF(AND(C52="Operation",DebtEnabled="Yes",Timeline_M!D52>=L2,Timeline_M!D52<L2+DebtTenor*12,I51>0),MIN(K2,I51),0) | G52: =E52+F52 | H52: =IF(AND(C52="Operation",Timeline_M!D52=L2,DebtEnabled="Yes"),TotalDebt*UpfrontFee/10000,0) | I52: =I51+D52-F52
A53: =Timeline_M!A53 | B53: =Timeline_M!B53 | C53: =Timeline_M!C53 | D53: =IF(AND(C53<>"Operation",DebtEnabled="Yes"),CAPEX_M!G53*DebtPct/100,0) | E53: =IF(AND(C53="Operation",DebtEnabled="Yes"),I52*DebtRate/100/12,0) | F53: =IF(AND(C53="Operation",DebtEnabled="Yes",Timeline_M!D53>=L2,Timeline_M!D53<L2+DebtTenor*12,I52>0),MIN(K2,I52),0) | G53: =E53+F53 | H53: =IF(AND(C53="Operation",Timeline_M!D53=L2,DebtEnabled="Yes"),TotalDebt*UpfrontFee/10000,0) | I53: =I52+D53-F53
A54: =Timeline_M!A54 | B54: =Timeline_M!B54 | C54: =Timeline_M!C54 | D54: =IF(AND(C54<>"Operation",DebtEnabled="Yes"),CAPEX_M!G54*DebtPct/100,0) | E54: =IF(AND(C54="Operation",DebtEnabled="Yes"),I53*DebtRate/100/12,0) | F54: =IF(AND(C54="Operation",DebtEnabled="Yes",Timeline_M!D54>=L2,Timeline_M!D54<L2+DebtTenor*12,I53>0),MIN(K2,I53),0) | G54: =E54+F54 | H54: =IF(AND(C54="Operation",Timeline_M!D54=L2,DebtEnabled="Yes"),TotalDebt*UpfrontFee/10000,0) | I54: =I53+D54-F54
A55: =Timeline_M!A55 | B55: =Timeline_M!B55 | C55: =Timeline_M!C55 | D55: =IF(AND(C55<>"Operation",DebtEnabled="Yes"),CAPEX_M!G55*DebtPct/100,0) | E55: =IF(AND(C55="Operation",DebtEnabled="Yes"),I54*DebtRate/100/12,0) | F55: =IF(AND(C55="Operation",DebtEnabled="Yes",Timeline_M!D55>=L2,Timeline_M!D55<L2+DebtTenor*12,I54>0),MIN(K2,I54),0) | G55: =E55+F55 | H55: =IF(AND(C55="Operation",Timeline_M!D55=L2,DebtEnabled="Yes"),TotalDebt*UpfrontFee/10000,0) | I55: =I54+D55-F55
A56: =Timeline_M!A56 | B56: =Timeline_M!B56 | C56: =Timeline_M!C56 | D56: =IF(AND(C56<>"Operation",DebtEnabled="Yes"),CAPEX_M!G56*DebtPct/100,0) | E56: =IF(AND(C56="Operation",DebtEnabled="Yes"),I55*DebtRate/100/12,0) | F56: =IF(AND(C56="Operation",DebtEnabled="Yes",Timeline_M!D56>=L2,Timeline_M!D56<L2+DebtTenor*12,I55>0),MIN(K2,I55),0) | G56: =E56+F56 | H56: =IF(AND(C56="Operation",Timeline_M!D56=L2,DebtEnabled="Yes"),TotalDebt*UpfrontFee/10000,0) | I56: =I55+D56-F56
A57: =Timeline_M!A57 | B57: =Timeline_M!B57 | C57: =Timeline_M!C57 | D57: =IF(AND(C57<>"Operation",DebtEnabled="Yes"),CAPEX_M!G57*DebtPct/100,0) | E57: =IF(AND(C57="Operation",DebtEnabled="Yes"),I56*DebtRate/100/12,0) | F57: =IF(AND(C57="Operation",DebtEnabled="Yes",Timeline_M!D57>=L2,Timeline_M!D57<L2+DebtTenor*12,I56>0),MIN(K2,I56),0) | G57: =E57+F57 | H57: =IF(AND(C57="Operation",Timeline_M!D57=L2,DebtEnabled="Yes"),TotalDebt*UpfrontFee/10000,0) | I57: =I56+D57-F57
A58: =Timeline_M!A58 | B58: =Timeline_M!B58 | C58: =Timeline_M!C58 | D58: =IF(AND(C58<>"Operation",DebtEnabled="Yes"),CAPEX_M!G58*DebtPct/100,0) | E58: =IF(AND(C58="Operation",DebtEnabled="Yes"),I57*DebtRate/100/12,0) | F58: =IF(AND(C58="Operation",DebtEnabled="Yes",Timeline_M!D58>=L2,Timeline_M!D58<L2+DebtTenor*12,I57>0),MIN(K2,I57),0) | G58: =E58+F58 | H58: =IF(AND(C58="Operation",Timeline_M!D58=L2,DebtEnabled="Yes"),TotalDebt*UpfrontFee/10000,0) | I58: =I57+D58-F58
A59: =Timeline_M!A59 | B59: =Timeline_M!B59 | C59: =Timeline_M!C59 | D59: =IF(AND(C59<>"Operation",DebtEnabled="Yes"),CAPEX_M!G59*DebtPct/100,0) | E59: =IF(AND(C59="Operation",DebtEnabled="Yes"),I58*DebtRate/100/12,0) | F59: =IF(AND(C59="Operation",DebtEnabled="Yes",Timeline_M!D59>=L2,Timeline_M!D59<L2+DebtTenor*12,I58>0),MIN(K2,I58),0) | G59: =E59+F59 | H59: =IF(AND(C59="Operation",Timeline_M!D59=L2,DebtEnabled="Yes"),TotalDebt*UpfrontFee/10000,0) | I59: =I58+D59-F59
A60: =Timeline_M!A60 | B60: =Timeline_M!B60 | C60: =Timeline_M!C60 | D60: =IF(AND(C60<>"Operation",DebtEnabled="Yes"),CAPEX_M!G60*DebtPct/100,0) | E60: =IF(AND(C60="Operation",DebtEnabled="Yes"),I59*DebtRate/100/12,0) | F60: =IF(AND(C60="Operation",DebtEnabled="Yes",Timeline_M!D60>=L2,Timeline_M!D60<L2+DebtTenor*12,I59>0),MIN(K2,I59),0) | G60: =E60+F60 | H60: =IF(AND(C60="Operation",Timeline_M!D60=L2,DebtEnabled="Yes"),TotalDebt*UpfrontFee/10000,0) | I60: =I59+D60-F60
A61: =Timeline_M!A61 | B61: =Timeline_M!B61 | C61: =Timeline_M!C61 | D61: =IF(AND(C61<>"Operation",DebtEnabled="Yes"),CAPEX_M!G61*DebtPct/100,0) | E61: =IF(AND(C61="Operation",DebtEnabled="Yes"),I60*DebtRate/100/12,0) | F61: =IF(AND(C61="Operation",DebtEnabled="Yes",Timeline_M!D61>=L2,Timeline_M!D61<L2+DebtTenor*12,I60>0),MIN(K2,I60),0) | G61: =E61+F61 | H61: =IF(AND(C61="Operation",Timeline_M!D61=L2,DebtEnabled="Yes"),TotalDebt*UpfrontFee/10000,0) | I61: =I60+D61-F61
A62: =Timeline_M!A62 | B62: =Timeline_M!B62 | C62: =Timeline_M!C62 | D62: =IF(AND(C62<>"Operation",DebtEnabled="Yes"),CAPEX_M!G62*DebtPct/100,0) | E62: =IF(AND(C62="Operation",DebtEnabled="Yes"),I61*DebtRate/100/12,0) | F62: =IF(AND(C62="Operation",DebtEnabled="Yes",Timeline_M!D62>=L2,Timeline_M!D62<L2+DebtTenor*12,I61>0),MIN(K2,I61),0) | G62: =E62+F62 | H62: =IF(AND(C62="Operation",Timeline_M!D62=L2,DebtEnabled="Yes"),TotalDebt*UpfrontFee/10000,0) | I62: =I61+D62-F62
A63: =Timeline_M!A63 | B63: =Timeline_M!B63 | C63: =Timeline_M!C63 | D63: =IF(AND(C63<>"Operation",DebtEnabled="Yes"),CAPEX_M!G63*DebtPct/100,0) | E63: =IF(AND(C63="Operation",DebtEnabled="Yes"),I62*DebtRate/100/12,0) | F63: =IF(AND(C63="Operation",DebtEnabled="Yes",Timeline_M!D63>=L2,Timeline_M!D63<L2+DebtTenor*12,I62>0),MIN(K2,I62),0) | G63: =E63+F63 | H63: =IF(AND(C63="Operation",Timeline_M!D63=L2,DebtEnabled="Yes"),TotalDebt*UpfrontFee/10000,0) | I63: =I62+D63-F63
A64: =Timeline_M!A64 | B64: =Timeline_M!B64 | C64: =Timeline_M!C64 | D64: =IF(AND(C64<>"Operation",DebtEnabled="Yes"),CAPEX_M!G64*DebtPct/100,0) | E64: =IF(AND(C64="Operation",DebtEnabled="Yes"),I63*DebtRate/100/12,0) | F64: =IF(AND(C64="Operation",DebtEnabled="Yes",Timeline_M!D64>=L2,Timeline_M!D64<L2+DebtTenor*12,I63>0),MIN(K2,I63),0) | G64: =E64+F64 | H64: =IF(AND(C64="Operation",Timeline_M!D64=L2,DebtEnabled="Yes"),TotalDebt*UpfrontFee/10000,0) | I64: =I63+D64-F64
A65: =Timeline_M!A65 | B65: =Timeline_M!B65 | C65: =Timeline_M!C65 | D65: =IF(AND(C65<>"Operation",DebtEnabled="Yes"),CAPEX_M!G65*DebtPct/100,0) | E65: =IF(AND(C65="Operation",DebtEnabled="Yes"),I64*DebtRate/100/12,0) | F65: =IF(AND(C65="Operation",DebtEnabled="Yes",Timeline_M!D65>=L2,Timeline_M!D65<L2+DebtTenor*12,I64>0),MIN(K2,I64),0) | G65: =E65+F65 | H65: =IF(AND(C65="Operation",Timeline_M!D65=L2,DebtEnabled="Yes"),TotalDebt*UpfrontFee/10000,0) | I65: =I64+D65-F65
A66: =Timeline_M!A66 | B66: =Timeline_M!B66 | C66: =Timeline_M!C66 | D66: =IF(AND(C66<>"Operation",DebtEnabled="Yes"),CAPEX_M!G66*DebtPct/100,0) | E66: =IF(AND(C66="Operation",DebtEnabled="Yes"),I65*DebtRate/100/12,0) | F66: =IF(AND(C66="Operation",DebtEnabled="Yes",Timeline_M!D66>=L2,Timeline_M!D66<L2+DebtTenor*12,I65>0),MIN(K2,I65),0) | G66: =E66+F66 | H66: =IF(AND(C66="Operation",Timeline_M!D66=L2,DebtEnabled="Yes"),TotalDebt*UpfrontFee/10000,0) | I66: =I65+D66-F66
A67: =Timeline_M!A67 | B67: =Timeline_M!B67 | C67: =Timeline_M!C67 | D67: =IF(AND(C67<>"Operation",DebtEnabled="Yes"),CAPEX_M!G67*DebtPct/100,0) | E67: =IF(AND(C67="Operation",DebtEnabled="Yes"),I66*DebtRate/100/12,0) | F67: =IF(AND(C67="Operation",DebtEnabled="Yes",Timeline_M!D67>=L2,Timeline_M!D67<L2+DebtTenor*12,I66>0),MIN(K2,I66),0) | G67: =E67+F67 | H67: =IF(AND(C67="Operation",Timeline_M!D67=L2,DebtEnabled="Yes"),TotalDebt*UpfrontFee/10000,0) | I67: =I66+D67-F67
A68: =Timeline_M!A68 | B68: =Timeline_M!B68 | C68: =Timeline_M!C68 | D68: =IF(AND(C68<>"Operation",DebtEnabled="Yes"),CAPEX_M!G68*DebtPct/100,0) | E68: =IF(AND(C68="Operation",DebtEnabled="Yes"),I67*DebtRate/100/12,0) | F68: =IF(AND(C68="Operation",DebtEnabled="Yes",Timeline_M!D68>=L2,Timeline_M!D68<L2+DebtTenor*12,I67>0),MIN(K2,I67),0) | G68: =E68+F68 | H68: =IF(AND(C68="Operation",Timeline_M!D68=L2,DebtEnabled="Yes"),TotalDebt*UpfrontFee/10000,0) | I68: =I67+D68-F68
A69: =Timeline_M!A69 | B69: =Timeline_M!B69 | C69: =Timeline_M!C69 | D69: =IF(AND(C69<>"Operation",DebtEnabled="Yes"),CAPEX_M!G69*DebtPct/100,0) | E69: =IF(AND(C69="Operation",DebtEnabled="Yes"),I68*DebtRate/100/12,0) | F69: =IF(AND(C69="Operation",DebtEnabled="Yes",Timeline_M!D69>=L2,Timeline_M!D69<L2+DebtTenor*12,I68>0),MIN(K2,I68),0) | G69: =E69+F69 | H69: =IF(AND(C69="Operation",Timeline_M!D69=L2,DebtEnabled="Yes"),TotalDebt*UpfrontFee/10000,0) | I69: =I68+D69-F69
A70: =Timeline_M!A70 | B70: =Timeline_M!B70 | C70: =Timeline_M!C70 | D70: =IF(AND(C70<>"Operation",DebtEnabled="Yes"),CAPEX_M!G70*DebtPct/100,0) | E70: =IF(AND(C70="Operation",DebtEnabled="Yes"),I69*DebtRate/100/12,0) | F70: =IF(AND(C70="Operation",DebtEnabled="Yes",Timeline_M!D70>=L2,Timeline_M!D70<L2+DebtTenor*12,I69>0),MIN(K2,I69),0) | G70: =E70+F70 | H70: =IF(AND(C70="Operation",Timeline_M!D70=L2,DebtEnabled="Yes"),TotalDebt*UpfrontFee/10000,0) | I70: =I69+D70-F70
A71: =Timeline_M!A71 | B71: =Timeline_M!B71 | C71: =Timeline_M!C71 | D71: =IF(AND(C71<>"Operation",DebtEnabled="Yes"),CAPEX_M!G71*DebtPct/100,0) | E71: =IF(AND(C71="Operation",DebtEnabled="Yes"),I70*DebtRate/100/12,0) | F71: =IF(AND(C71="Operation",DebtEnabled="Yes",Timeline_M!D71>=L2,Timeline_M!D71<L2+DebtTenor*12,I70>0),MIN(K2,I70),0) | G71: =E71+F71 | H71: =IF(AND(C71="Operation",Timeline_M!D71=L2,DebtEnabled="Yes"),TotalDebt*UpfrontFee/10000,0) | I71: =I70+D71-F71
A72: =Timeline_M!A72 | B72: =Timeline_M!B72 | C72: =Timeline_M!C72 | D72: =IF(AND(C72<>"Operation",DebtEnabled="Yes"),CAPEX_M!G72*DebtPct/100,0) | E72: =IF(AND(C72="Operation",DebtEnabled="Yes"),I71*DebtRate/100/12,0) | F72: =IF(AND(C72="Operation",DebtEnabled="Yes",Timeline_M!D72>=L2,Timeline_M!D72<L2+DebtTenor*12,I71>0),MIN(K2,I71),0) | G72: =E72+F72 | H72: =IF(AND(C72="Operation",Timeline_M!D72=L2,DebtEnabled="Yes"),TotalDebt*UpfrontFee/10000,0) | I72: =I71+D72-F72
A73: =Timeline_M!A73 | B73: =Timeline_M!B73 | C73: =Timeline_M!C73 | D73: =IF(AND(C73<>"Operation",DebtEnabled="Yes"),CAPEX_M!G73*DebtPct/100,0) | E73: =IF(AND(C73="Operation",DebtEnabled="Yes"),I72*DebtRate/100/12,0) | F73: =IF(AND(C73="Operation",DebtEnabled="Yes",Timeline_M!D73>=L2,Timeline_M!D73<L2+DebtTenor*12,I72>0),MIN(K2,I72),0) | G73: =E73+F73 | H73: =IF(AND(C73="Operation",Timeline_M!D73=L2,DebtEnabled="Yes"),TotalDebt*UpfrontFee/10000,0) | I73: =I72+D73-F73
A74: =Timeline_M!A74 | B74: =Timeline_M!B74 | C74: =Timeline_M!C74 | D74: =IF(AND(C74<>"Operation",DebtEnabled="Yes"),CAPEX_M!G74*DebtPct/100,0) | E74: =IF(AND(C74="Operation",DebtEnabled="Yes"),I73*DebtRate/100/12,0) | F74: =IF(AND(C74="Operation",DebtEnabled="Yes",Timeline_M!D74>=L2,Timeline_M!D74<L2+DebtTenor*12,I73>0),MIN(K2,I73),0) | G74: =E74+F74 | H74: =IF(AND(C74="Operation",Timeline_M!D74=L2,DebtEnabled="Yes"),TotalDebt*UpfrontFee/10000,0) | I74: =I73+D74-F74
A75: =Timeline_M!A75 | B75: =Timeline_M!B75 | C75: =Timeline_M!C75 | D75: =IF(AND(C75<>"Operation",DebtEnabled="Yes"),CAPEX_M!G75*DebtPct/100,0) | E75: =IF(AND(C75="Operation",DebtEnabled="Yes"),I74*DebtRate/100/12,0) | F75: =IF(AND(C75="Operation",DebtEnabled="Yes",Timeline_M!D75>=L2,Timeline_M!D75<L2+DebtTenor*12,I74>0),MIN(K2,I74),0) | G75: =E75+F75 | H75: =IF(AND(C75="Operation",Timeline_M!D75=L2,DebtEnabled="Yes"),TotalDebt*UpfrontFee/10000,0) | I75: =I74+D75-F75
A76: =Timeline_M!A76 | B76: =Timeline_M!B76 | C76: =Timeline_M!C76 | D76: =IF(AND(C76<>"Operation",DebtEnabled="Yes"),CAPEX_M!G76*DebtPct/100,0) | E76: =IF(AND(C76="Operation",DebtEnabled="Yes"),I75*DebtRate/100/12,0) | F76: =IF(AND(C76="Operation",DebtEnabled="Yes",Timeline_M!D76>=L2,Timeline_M!D76<L2+DebtTenor*12,I75>0),MIN(K2,I75),0) | G76: =E76+F76 | H76: =IF(AND(C76="Operation",Timeline_M!D76=L2,DebtEnabled="Yes"),TotalDebt*UpfrontFee/10000,0) | I76: =I75+D76-F76
A77: =Timeline_M!A77 | B77: =Timeline_M!B77 | C77: =Timeline_M!C77 | D77: =IF(AND(C77<>"Operation",DebtEnabled="Yes"),CAPEX_M!G77*DebtPct/100,0) | E77: =IF(AND(C77="Operation",DebtEnabled="Yes"),I76*DebtRate/100/12,0) | F77: =IF(AND(C77="Operation",DebtEnabled="Yes",Timeline_M!D77>=L2,Timeline_M!D77<L2+DebtTenor*12,I76>0),MIN(K2,I76),0) | G77: =E77+F77 | H77: =IF(AND(C77="Operation",Timeline_M!D77=L2,DebtEnabled="Yes"),TotalDebt*UpfrontFee/10000,0) | I77: =I76+D77-F77
A78: =Timeline_M!A78 | B78: =Timeline_M!B78 | C78: =Timeline_M!C78 | D78: =IF(AND(C78<>"Operation",DebtEnabled="Yes"),CAPEX_M!G78*DebtPct/100,0) | E78: =IF(AND(C78="Operation",DebtEnabled="Yes"),I77*DebtRate/100/12,0) | F78: =IF(AND(C78="Operation",DebtEnabled="Yes",Timeline_M!D78>=L2,Timeline_M!D78<L2+DebtTenor*12,I77>0),MIN(K2,I77),0) | G78: =E78+F78 | H78: =IF(AND(C78="Operation",Timeline_M!D78=L2,DebtEnabled="Yes"),TotalDebt*UpfrontFee/10000,0) | I78: =I77+D78-F78
A79: =Timeline_M!A79 | B79: =Timeline_M!B79 | C79: =Timeline_M!C79 | D79: =IF(AND(C79<>"Operation",DebtEnabled="Yes"),CAPEX_M!G79*DebtPct/100,0) | E79: =IF(AND(C79="Operation",DebtEnabled="Yes"),I78*DebtRate/100/12,0) | F79: =IF(AND(C79="Operation",DebtEnabled="Yes",Timeline_M!D79>=L2,Timeline_M!D79<L2+DebtTenor*12,I78>0),MIN(K2,I78),0) | G79: =E79+F79 | H79: =IF(AND(C79="Operation",Timeline_M!D79=L2,DebtEnabled="Yes"),TotalDebt*UpfrontFee/10000,0) | I79: =I78+D79-F79
A80: =Timeline_M!A80 | B80: =Timeline_M!B80 | C80: =Timeline_M!C80 | D80: =IF(AND(C80<>"Operation",DebtEnabled="Yes"),CAPEX_M!G80*DebtPct/100,0) | E80: =IF(AND(C80="Operation",DebtEnabled="Yes"),I79*DebtRate/100/12,0) | F80: =IF(AND(C80="Operation",DebtEnabled="Yes",Timeline_M!D80>=L2,Timeline_M!D80<L2+DebtTenor*12,I79>0),MIN(K2,I79),0) | G80: =E80+F80 | H80: =IF(AND(C80="Operation",Timeline_M!D80=L2,DebtEnabled="Yes"),TotalDebt*UpfrontFee/10000,0) | I80: =I79+D80-F80
A81: =Timeline_M!A81 | B81: =Timeline_M!B81 | C81: =Timeline_M!C81 | D81: =IF(AND(C81<>"Operation",DebtEnabled="Yes"),CAPEX_M!G81*DebtPct/100,0) | E81: =IF(AND(C81="Operation",DebtEnabled="Yes"),I80*DebtRate/100/12,0) | F81: =IF(AND(C81="Operation",DebtEnabled="Yes",Timeline_M!D81>=L2,Timeline_M!D81<L2+DebtTenor*12,I80>0),MIN(K2,I80),0) | G81: =E81+F81 | H81: =IF(AND(C81="Operation",Timeline_M!D81=L2,DebtEnabled="Yes"),TotalDebt*UpfrontFee/10000,0) | I81: =I80+D81-F81
A82: =Timeline_M!A82 | B82: =Timeline_M!B82 | C82: =Timeline_M!C82 | D82: =IF(AND(C82<>"Operation",DebtEnabled="Yes"),CAPEX_M!G82*DebtPct/100,0) | E82: =IF(AND(C82="Operation",DebtEnabled="Yes"),I81*DebtRate/100/12,0) | F82: =IF(AND(C82="Operation",DebtEnabled="Yes",Timeline_M!D82>=L2,Timeline_M!D82<L2+DebtTenor*12,I81>0),MIN(K2,I81),0) | G82: =E82+F82 | H82: =IF(AND(C82="Operation",Timeline_M!D82=L2,DebtEnabled="Yes"),TotalDebt*UpfrontFee/10000,0) | I82: =I81+D82-F82
A83: =Timeline_M!A83 | B83: =Timeline_M!B83 | C83: =Timeline_M!C83 | D83: =IF(AND(C83<>"Operation",DebtEnabled="Yes"),CAPEX_M!G83*DebtPct/100,0) | E83: =IF(AND(C83="Operation",DebtEnabled="Yes"),I82*DebtRate/100/12,0) | F83: =IF(AND(C83="Operation",DebtEnabled="Yes",Timeline_M!D83>=L2,Timeline_M!D83<L2+DebtTenor*12,I82>0),MIN(K2,I82),0) | G83: =E83+F83 | H83: =IF(AND(C83="Operation",Timeline_M!D83=L2,DebtEnabled="Yes"),TotalDebt*UpfrontFee/10000,0) | I83: =I82+D83-F83
A84: =Timeline_M!A84 | B84: =Timeline_M!B84 | C84: =Timeline_M!C84 | D84: =IF(AND(C84<>"Operation",DebtEnabled="Yes"),CAPEX_M!G84*DebtPct/100,0) | E84: =IF(AND(C84="Operation",DebtEnabled="Yes"),I83*DebtRate/100/12,0) | F84: =IF(AND(C84="Operation",DebtEnabled="Yes",Timeline_M!D84>=L2,Timeline_M!D84<L2+DebtTenor*12,I83>0),MIN(K2,I83),0) | G84: =E84+F84 | H84: =IF(AND(C84="Operation",Timeline_M!D84=L2,DebtEnabled="Yes"),TotalDebt*UpfrontFee/10000,0) | I84: =I83+D84-F84
A85: =Timeline_M!A85 | B85: =Timeline_M!B85 | C85: =Timeline_M!C85 | D85: =IF(AND(C85<>"Operation",DebtEnabled="Yes"),CAPEX_M!G85*DebtPct/100,0) | E85: =IF(AND(C85="Operation",DebtEnabled="Yes"),I84*DebtRate/100/12,0) | F85: =IF(AND(C85="Operation",DebtEnabled="Yes",Timeline_M!D85>=L2,Timeline_M!D85<L2+DebtTenor*12,I84>0),MIN(K2,I84),0) | G85: =E85+F85 | H85: =IF(AND(C85="Operation",Timeline_M!D85=L2,DebtEnabled="Yes"),TotalDebt*UpfrontFee/10000,0) | I85: =I84+D85-F85
A86: =Timeline_M!A86 | B86: =Timeline_M!B86 | C86: =Timeline_M!C86 | D86: =IF(AND(C86<>"Operation",DebtEnabled="Yes"),CAPEX_M!G86*DebtPct/100,0) | E86: =IF(AND(C86="Operation",DebtEnabled="Yes"),I85*DebtRate/100/12,0) | F86: =IF(AND(C86="Operation",DebtEnabled="Yes",Timeline_M!D86>=L2,Timeline_M!D86<L2+DebtTenor*12,I85>0),MIN(K2,I85),0) | G86: =E86+F86 | H86: =IF(AND(C86="Operation",Timeline_M!D86=L2,DebtEnabled="Yes"),TotalDebt*UpfrontFee/10000,0) | I86: =I85+D86-F86
A87: =Timeline_M!A87 | B87: =Timeline_M!B87 | C87: =Timeline_M!C87 | D87: =IF(AND(C87<>"Operation",DebtEnabled="Yes"),CAPEX_M!G87*DebtPct/100,0) | E87: =IF(AND(C87="Operation",DebtEnabled="Yes"),I86*DebtRate/100/12,0) | F87: =IF(AND(C87="Operation",DebtEnabled="Yes",Timeline_M!D87>=L2,Timeline_M!D87<L2+DebtTenor*12,I86>0),MIN(K2,I86),0) | G87: =E87+F87 | H87: =IF(AND(C87="Operation",Timeline_M!D87=L2,DebtEnabled="Yes"),TotalDebt*UpfrontFee/10000,0) | I87: =I86+D87-F87
A88: =Timeline_M!A88 | B88: =Timeline_M!B88 | C88: =Timeline_M!C88 | D88: =IF(AND(C88<>"Operation",DebtEnabled="Yes"),CAPEX_M!G88*DebtPct/100,0) | E88: =IF(AND(C88="Operation",DebtEnabled="Yes"),I87*DebtRate/100/12,0) | F88: =IF(AND(C88="Operation",DebtEnabled="Yes",Timeline_M!D88>=L2,Timeline_M!D88<L2+DebtTenor*12,I87>0),MIN(K2,I87),0) | G88: =E88+F88 | H88: =IF(AND(C88="Operation",Timeline_M!D88=L2,DebtEnabled="Yes"),TotalDebt*UpfrontFee/10000,0) | I88: =I87+D88-F88
A89: =Timeline_M!A89 | B89: =Timeline_M!B89 | C89: =Timeline_M!C89 | D89: =IF(AND(C89<>"Operation",DebtEnabled="Yes"),CAPEX_M!G89*DebtPct/100,0) | E89: =IF(AND(C89="Operation",DebtEnabled="Yes"),I88*DebtRate/100/12,0) | F89: =IF(AND(C89="Operation",DebtEnabled="Yes",Timeline_M!D89>=L2,Timeline_M!D89<L2+DebtTenor*12,I88>0),MIN(K2,I88),0) | G89: =E89+F89 | H89: =IF(AND(C89="Operation",Timeline_M!D89=L2,DebtEnabled="Yes"),TotalDebt*UpfrontFee/10000,0) | I89: =I88+D89-F89
A90: =Timeline_M!A90 | B90: =Timeline_M!B90 | C90: =Timeline_M!C90 | D90: =IF(AND(C90<>"Operation",DebtEnabled="Yes"),CAPEX_M!G90*DebtPct/100,0) | E90: =IF(AND(C90="Operation",DebtEnabled="Yes"),I89*DebtRate/100/12,0) | F90: =IF(AND(C90="Operation",DebtEnabled="Yes",Timeline_M!D90>=L2,Timeline_M!D90<L2+DebtTenor*12,I89>0),MIN(K2,I89),0) | G90: =E90+F90 | H90: =IF(AND(C90="Operation",Timeline_M!D90=L2,DebtEnabled="Yes"),TotalDebt*UpfrontFee/10000,0) | I90: =I89+D90-F90
A91: =Timeline_M!A91 | B91: =Timeline_M!B91 | C91: =Timeline_M!C91 | D91: =IF(AND(C91<>"Operation",DebtEnabled="Yes"),CAPEX_M!G91*DebtPct/100,0) | E91: =IF(AND(C91="Operation",DebtEnabled="Yes"),I90*DebtRate/100/12,0) | F91: =IF(AND(C91="Operation",DebtEnabled="Yes",Timeline_M!D91>=L2,Timeline_M!D91<L2+DebtTenor*12,I90>0),MIN(K2,I90),0) | G91: =E91+F91 | H91: =IF(AND(C91="Operation",Timeline_M!D91=L2,DebtEnabled="Yes"),TotalDebt*UpfrontFee/10000,0) | I91: =I90+D91-F91
A92: =Timeline_M!A92 | B92: =Timeline_M!B92 | C92: =Timeline_M!C92 | D92: =IF(AND(C92<>"Operation",DebtEnabled="Yes"),CAPEX_M!G92*DebtPct/100,0) | E92: =IF(AND(C92="Operation",DebtEnabled="Yes"),I91*DebtRate/100/12,0) | F92: =IF(AND(C92="Operation",DebtEnabled="Yes",Timeline_M!D92>=L2,Timeline_M!D92<L2+DebtTenor*12,I91>0),MIN(K2,I91),0) | G92: =E92+F92 | H92: =IF(AND(C92="Operation",Timeline_M!D92=L2,DebtEnabled="Yes"),TotalDebt*UpfrontFee/10000,0) | I92: =I91+D92-F92
A93: =Timeline_M!A93 | B93: =Timeline_M!B93 | C93: =Timeline_M!C93 | D93: =IF(AND(C93<>"Operation",DebtEnabled="Yes"),CAPEX_M!G93*DebtPct/100,0) | E93: =IF(AND(C93="Operation",DebtEnabled="Yes"),I92*DebtRate/100/12,0) | F93: =IF(AND(C93="Operation",DebtEnabled="Yes",Timeline_M!D93>=L2,Timeline_M!D93<L2+DebtTenor*12,I92>0),MIN(K2,I92),0) | G93: =E93+F93 | H93: =IF(AND(C93="Operation",Timeline_M!D93=L2,DebtEnabled="Yes"),TotalDebt*UpfrontFee/10000,0) | I93: =I92+D93-F93
A94: =Timeline_M!A94 | B94: =Timeline_M!B94 | C94: =Timeline_M!C94 | D94: =IF(AND(C94<>"Operation",DebtEnabled="Yes"),CAPEX_M!G94*DebtPct/100,0) | E94: =IF(AND(C94="Operation",DebtEnabled="Yes"),I93*DebtRate/100/12,0) | F94: =IF(AND(C94="Operation",DebtEnabled="Yes",Timeline_M!D94>=L2,Timeline_M!D94<L2+DebtTenor*12,I93>0),MIN(K2,I93),0) | G94: =E94+F94 | H94: =IF(AND(C94="Operation",Timeline_M!D94=L2,DebtEnabled="Yes"),TotalDebt*UpfrontFee/10000,0) | I94: =I93+D94-F94
A95: =Timeline_M!A95 | B95: =Timeline_M!B95 | C95: =Timeline_M!C95 | D95: =IF(AND(C95<>"Operation",DebtEnabled="Yes"),CAPEX_M!G95*DebtPct/100,0) | E95: =IF(AND(C95="Operation",DebtEnabled="Yes"),I94*DebtRate/100/12,0) | F95: =IF(AND(C95="Operation",DebtEnabled="Yes",Timeline_M!D95>=L2,Timeline_M!D95<L2+DebtTenor*12,I94>0),MIN(K2,I94),0) | G95: =E95+F95 | H95: =IF(AND(C95="Operation",Timeline_M!D95=L2,DebtEnabled="Yes"),TotalDebt*UpfrontFee/10000,0) | I95: =I94+D95-F95
A96: =Timeline_M!A96 | B96: =Timeline_M!B96 | C96: =Timeline_M!C96 | D96: =IF(AND(C96<>"Operation",DebtEnabled="Yes"),CAPEX_M!G96*DebtPct/100,0) | E96: =IF(AND(C96="Operation",DebtEnabled="Yes"),I95*DebtRate/100/12,0) | F96: =IF(AND(C96="Operation",DebtEnabled="Yes",Timeline_M!D96>=L2,Timeline_M!D96<L2+DebtTenor*12,I95>0),MIN(K2,I95),0) | G96: =E96+F96 | H96: =IF(AND(C96="Operation",Timeline_M!D96=L2,DebtEnabled="Yes"),TotalDebt*UpfrontFee/10000,0) | I96: =I95+D96-F96
A97: =Timeline_M!A97 | B97: =Timeline_M!B97 | C97: =Timeline_M!C97 | D97: =IF(AND(C97<>"Operation",DebtEnabled="Yes"),CAPEX_M!G97*DebtPct/100,0) | E97: =IF(AND(C97="Operation",DebtEnabled="Yes"),I96*DebtRate/100/12,0) | F97: =IF(AND(C97="Operation",DebtEnabled="Yes",Timeline_M!D97>=L2,Timeline_M!D97<L2+DebtTenor*12,I96>0),MIN(K2,I96),0) | G97: =E97+F97 | H97: =IF(AND(C97="Operation",Timeline_M!D97=L2,DebtEnabled="Yes"),TotalDebt*UpfrontFee/10000,0) | I97: =I96+D97-F97
A98: =Timeline_M!A98 | B98: =Timeline_M!B98 | C98: =Timeline_M!C98 | D98: =IF(AND(C98<>"Operation",DebtEnabled="Yes"),CAPEX_M!G98*DebtPct/100,0) | E98: =IF(AND(C98="Operation",DebtEnabled="Yes"),I97*DebtRate/100/12,0) | F98: =IF(AND(C98="Operation",DebtEnabled="Yes",Timeline_M!D98>=L2,Timeline_M!D98<L2+DebtTenor*12,I97>0),MIN(K2,I97),0) | G98: =E98+F98 | H98: =IF(AND(C98="Operation",Timeline_M!D98=L2,DebtEnabled="Yes"),TotalDebt*UpfrontFee/10000,0) | I98: =I97+D98-F98
A99: =Timeline_M!A99 | B99: =Timeline_M!B99 | C99: =Timeline_M!C99 | D99: =IF(AND(C99<>"Operation",DebtEnabled="Yes"),CAPEX_M!G99*DebtPct/100,0) | E99: =IF(AND(C99="Operation",DebtEnabled="Yes"),I98*DebtRate/100/12,0) | F99: =IF(AND(C99="Operation",DebtEnabled="Yes",Timeline_M!D99>=L2,Timeline_M!D99<L2+DebtTenor*12,I98>0),MIN(K2,I98),0) | G99: =E99+F99 | H99: =IF(AND(C99="Operation",Timeline_M!D99=L2,DebtEnabled="Yes"),TotalDebt*UpfrontFee/10000,0) | I99: =I98+D99-F99
A100: =Timeline_M!A100 | B100: =Timeline_M!B100 | C100: =Timeline_M!C100 | D100: =IF(AND(C100<>"Operation",DebtEnabled="Yes"),CAPEX_M!G100*DebtPct/100,0) | E100: =IF(AND(C100="Operation",DebtEnabled="Yes"),I99*DebtRate/100/12,0) | F100: =IF(AND(C100="Operation",DebtEnabled="Yes",Timeline_M!D100>=L2,Timeline_M!D100<L2+DebtTenor*12,I99>0),MIN(K2,I99),0) | G100: =E100+F100 | H100: =IF(AND(C100="Operation",Timeline_M!D100=L2,DebtEnabled="Yes"),TotalDebt*UpfrontFee/10000,0) | I100: =I99+D100-F100
...

Sheet Cashflow_M
A1: Month | B1: Year | C1: Phase | D1: Revenue | E1: OPEX | F1: CAPEX | G1: UnleveredCF | H1: DebtDraw | I1: DebtService | J1: DebtFees | K1: EquityCF
A2: =Timeline_M!A2 | B2: =Timeline_M!B2 | C2: =Timeline_M!C2 | D2: =Revenue_M!G2 | E2: =OPEX_M!I2 | F2: =CAPEX_M!G2 | G2: =D2-E2-F2 | H2: =Debt_M!D2 | I2: =Debt_M!G2 | J2: =Debt_M!H2 | K2: =G2+H2-I2-J2
A3: =Timeline_M!A3 | B3: =Timeline_M!B3 | C3: =Timeline_M!C3 | D3: =Revenue_M!G3 | E3: =OPEX_M!I3 | F3: =CAPEX_M!G3 | G3: =D3-E3-F3 | H3: =Debt_M!D3 | I3: =Debt_M!G3 | J3: =Debt_M!H3 | K3: =G3+H3-I3-J3
A4: =Timeline_M!A4 | B4: =Timeline_M!B4 | C4: =Timeline_M!C4 | D4: =Revenue_M!G4 | E4: =OPEX_M!I4 | F4: =CAPEX_M!G4 | G4: =D4-E4-F4 | H4: =Debt_M!D4 | I4: =Debt_M!G4 | J4: =Debt_M!H4 | K4: =G4+H4-I4-J4
A5: =Timeline_M!A5 | B5: =Timeline_M!B5 | C5: =Timeline_M!C5 | D5: =Revenue_M!G5 | E5: =OPEX_M!I5 | F5: =CAPEX_M!G5 | G5: =D5-E5-F5 | H5: =Debt_M!D5 | I5: =Debt_M!G5 | J5: =Debt_M!H5 | K5: =G5+H5-I5-J5
A6: =Timeline_M!A6 | B6: =Timeline_M!B6 | C6: =Timeline_M!C6 | D6: =Revenue_M!G6 | E6: =OPEX_M!I6 | F6: =CAPEX_M!G6 | G6: =D6-E6-F6 | H6: =Debt_M!D6 | I6: =Debt_M!G6 | J6: =Debt_M!H6 | K6: =G6+H6-I6-J6
A7: =Timeline_M!A7 | B7: =Timeline_M!B7 | C7: =Timeline_M!C7 | D7: =Revenue_M!G7 | E7: =OPEX_M!I7 | F7: =CAPEX_M!G7 | G7: =D7-E7-F7 | H7: =Debt_M!D7 | I7: =Debt_M!G7 | J7: =Debt_M!H7 | K7: =G7+H7-I7-J7
A8: =Timeline_M!A8 | B8: =Timeline_M!B8 | C8: =Timeline_M!C8 | D8: =Revenue_M!G8 | E8: =OPEX_M!I8 | F8: =CAPEX_M!G8 | G8: =D8-E8-F8 | H8: =Debt_M!D8 | I8: =Debt_M!G8 | J8: =Debt_M!H8 | K8: =G8+H8-I8-J8
A9: =Timeline_M!A9 | B9: =Timeline_M!B9 | C9: =Timeline_M!C9 | D9: =Revenue_M!G9 | E9: =OPEX_M!I9 | F9: =CAPEX_M!G9 | G9: =D9-E9-F9 | H9: =Debt_M!D9 | I9: =Debt_M!G9 | J9: =Debt_M!H9 | K9: =G9+H9-I9-J9
A10: =Timeline_M!A10 | B10: =Timeline_M!B10 | C10: =Timeline_M!C10 | D10: =Revenue_M!G10 | E10: =OPEX_M!I10 | F10: =CAPEX_M!G10 | G10: =D10-E10-F10 | H10: =Debt_M!D10 | I10: =Debt_M!G10 | J10: =Debt_M!H10 | K10: =G10+H10-I10-J10
A11: =Timeline_M!A11 | B11: =Timeline_M!B11 | C11: =Timeline_M!C11 | D11: =Revenue_M!G11 | E11: =OPEX_M!I11 | F11: =CAPEX_M!G11 | G11: =D11-E11-F11 | H11: =Debt_M!D11 | I11: =Debt_M!G11 | J11: =Debt_M!H11 | K11: =G11+H11-I11-J11
A12: =Timeline_M!A12 | B12: =Timeline_M!B12 | C12: =Timeline_M!C12 | D12: =Revenue_M!G12 | E12: =OPEX_M!I12 | F12: =CAPEX_M!G12 | G12: =D12-E12-F12 | H12: =Debt_M!D12 | I12: =Debt_M!G12 | J12: =Debt_M!H12 | K12: =G12+H12-I12-J12
A13: =Timeline_M!A13 | B13: =Timeline_M!B13 | C13: =Timeline_M!C13 | D13: =Revenue_M!G13 | E13: =OPEX_M!I13 | F13: =CAPEX_M!G13 | G13: =D13-E13-F13 | H13: =Debt_M!D13 | I13: =Debt_M!G13 | J13: =Debt_M!H13 | K13: =G13+H13-I13-J13
... A500: =Timeline_M!A500 | B500: =Timeline_M!B500 | C500: =Timeline_M!C500 | D500: =Revenue_M!G500 | E500: =OPEX_M!I500 | F500: =CAPEX_M!G500 | G500: =D500-E500-F500 | H500: =Debt_M!D500 | I500: =Debt_M!G500 | J500: =Debt_M!H500 | K500: =G500+H500-I500-J500

Sheet Outputs
A1: OUTPUTS & CHECKS | D1: UnleveredCF_Dates | E1: UnleveredCF_Values | F1: EquityCF_Dates | G1: EquityCF_Values | H1: Sources | I1: Uses | J1: Diff | K1: DebtDraw_Check | L1: DebtBalance_Check
D2: =Cashflow_M!A2 | E2: =Cashflow_M!G2 | F2: =Cashflow_M!A2 | G2: =Cashflow_M!K2 | H2: =Cashflow_M!D2+Cashflow_M!H2 | I2: =Cashflow_M!E2+Cashflow_M!F2+Cashflow_M!I2+Cashflow_M!J2 | J2: =H2-I2 | K2: =IF(Cashflow_M!C2="Operation",ABS(Cashflow_M!H2),0) | L2: =Debt_M!I2
A3: SUMMARY METRICS | D3: =IF(Cashflow_M!A3<>"",Cashflow_M!A3,"") | E3: =IF(Cashflow_M!A3<>"",Cashflow_M!G3,"") | F3: =IF(Cashflow_M!A3<>"",Cashflow_M!A3,"") | G3: =IF(Cashflow_M!A3<>"",Cashflow_M!K3,"") | H3: =IF(Cashflow_M!A3<>"",Cashflow_M!D3+Cashflow_M!H3,"") | I3: =IF(Cashflow_M!A3<>"",Cashflow_M!E3+Cashflow_M!F3+Cashflow_M!I3+Cashflow_M!J3,"") | J3: =IF(Cashflow_M!A3<>"",H3-I3,"") | K3: =IF(Cashflow_M!C3="Operation",ABS(Cashflow_M!H3),0) | L3: =IF(Debt_M!A3<>"",Debt_M!I3,"")
A4: Total CAPEX (COP) | B4: =CapexDev+CapexCon+CapexCOD | D4: =IF(Cashflow_M!A4<>"",Cashflow_M!A4,"") | E4: =IF(Cashflow_M!A4<>"",Cashflow_M!G4,"") | F4: =IF(Cashflow_M!A4<>"",Cashflow_M!A4,"") | G4: =IF(Cashflow_M!A4<>"",Cashflow_M!K4,"") | H4: =IF(Cashflow_M!A4<>"",Cashflow_M!D4+Cashflow_M!H4,"") | I4: =IF(Cashflow_M!A4<>"",Cashflow_M!E4+Cashflow_M!F4+Cashflow_M!I4+Cashflow_M!J4,"") | J4: =IF(Cashflow_M!A4<>"",H4-I4,"") | K4: =IF(Cashflow_M!C4="Operation",ABS(Cashflow_M!H4),0) | L4: =IF(Debt_M!A4<>"",Debt_M!I4,"")
A5: Total Debt (COP) | B5: =SUM(Debt_M!D:D) | D5: =IF(Cashflow_M!A5<>"",Cashflow_M!A5,"") | E5: =IF(Cashflow_M!A5<>"",Cashflow_M!G5,"") | F5: =IF(Cashflow_M!A5<>"",Cashflow_M!A5,"") | G5: =IF(Cashflow_M!A5<>"",Cashflow_M!K5,"") | H5: =IF(Cashflow_M!A5<>"",Cashflow_M!D5+Cashflow_M!H5,"") | I5: =IF(Cashflow_M!A5<>"",Cashflow_M!E5+Cashflow_M!F5+Cashflow_M!I5+Cashflow_M!J5,"") | J5: =IF(Cashflow_M!A5<>"",H5-I5,"") | K5: =IF(Cashflow_M!C5="Operation",ABS(Cashflow_M!H5),0) | L5: =IF(Debt_M!A5<>"",Debt_M!I5,"")
A6: Total Equity (COP) | B6: =B4-B5 | D6: =IF(Cashflow_M!A6<>"",Cashflow_M!A6,"") | E6: =IF(Cashflow_M!A6<>"",Cashflow_M!G6,"") | F6: =IF(Cashflow_M!A6<>"",Cashflow_M!A6,"") | G6: =IF(Cashflow_M!A6<>"",Cashflow_M!K6,"") | H6: =IF(Cashflow_M!A6<>"",Cashflow_M!D6+Cashflow_M!H6,"") | I6: =IF(Cashflow_M!A6<>"",Cashflow_M!E6+Cashflow_M!F6+Cashflow_M!I6+Cashflow_M!J6,"") | J6: =IF(Cashflow_M!A6<>"",H6-I6,"") | K6: =IF(Cashflow_M!C6="Operation",ABS(Cashflow_M!H6),0) | L6: =IF(Debt_M!A6<>"",Debt_M!I6,"")
D7: =IF(Cashflow_M!A7<>"",Cashflow_M!A7,"") | E7: =IF(Cashflow_M!A7<>"",Cashflow_M!G7,"") | F7: =IF(Cashflow_M!A7<>"",Cashflow_M!A7,"") | G7: =IF(Cashflow_M!A7<>"",Cashflow_M!K7,"") | H7: =IF(Cashflow_M!A7<>"",Cashflow_M!D7+Cashflow_M!H7,"") | I7: =IF(Cashflow_M!A7<>"",Cashflow_M!E7+Cashflow_M!F7+Cashflow_M!I7+Cashflow_M!J7,"") | J7: =IF(Cashflow_M!A7<>"",H7-I7,"") | K7: =IF(Cashflow_M!C7="Operation",ABS(Cashflow_M!H7),0) | L7: =IF(Debt_M!A7<>"",Debt_M!I7,"")
A8: IRRs | D8: =IF(Cashflow_M!A8<>"",Cashflow_M!A8,"") | E8: =IF(Cashflow_M!A8<>"",Cashflow_M!G8,"") | F8: =IF(Cashflow_M!A8<>"",Cashflow_M!A8,"") | G8: =IF(Cashflow_M!A8<>"",Cashflow_M!K8,"") | H8: =IF(Cashflow_M!A8<>"",Cashflow_M!D8+Cashflow_M!H8,"") | I8: =IF(Cashflow_M!A8<>"",Cashflow_M!E8+Cashflow_M!F8+Cashflow_M!I8+Cashflow_M!J8,"") | J8: =IF(Cashflow_M!A8<>"",H8-I8,"") | K8: =IF(Cashflow_M!C8="Operation",ABS(Cashflow_M!H8),0) | L8: =IF(Debt_M!A8<>"",Debt_M!I8,"")
A9: Unlevered IRR (Pre-tax) | B9: =XIRR(E2:E501,D2:D501) | D9: =IF(Cashflow_M!A9<>"",Cashflow_M!A9,"") | E9: =IF(Cashflow_M!A9<>"",Cashflow_M!G9,"") | F9: =IF(Cashflow_M!A9<>"",Cashflow_M!A9,"") | G9: =IF(Cashflow_M!A9<>"",Cashflow_M!K9,"") | H9: =IF(Cashflow_M!A9<>"",Cashflow_M!D9+Cashflow_M!H9,"") | I9: =IF(Cashflow_M!A9<>"",Cashflow_M!E9+Cashflow_M!F9+Cashflow_M!I9+Cashflow_M!J9,"") | J9: =IF(Cashflow_M!A9<>"",H9-I9,"") | K9: =IF(Cashflow_M!C9="Operation",ABS(Cashflow_M!H9),0) | L9: =IF(Debt_M!A9<>"",Debt_M!I9,"")
A10: Equity IRR (After-tax) | B10: =XIRR(G2:G501,F2:F501) | D10: =IF(Cashflow_M!A10<>"",Cashflow_M!A10,"") | E10: =IF(Cashflow_M!A10<>"",Cashflow_M!G10,"") | F10: =IF(Cashflow_M!A10<>"",Cashflow_M!A10,"") | G10: =IF(Cashflow_M!A10<>"",Cashflow_M!K10,"") | H10: =IF(Cashflow_M!A10<>"",Cashflow_M!D10+Cashflow_M!H10,"") | I10: =IF(Cashflow_M!A10<>"",Cashflow_M!E10+Cashflow_M!F10+Cashflow_M!I10+Cashflow_M!J10,"") | J10: =IF(Cashflow_M!A10<>"",H10-I10,"") | K10: =IF(Cashflow_M!C10="Operation",ABS(Cashflow_M!H10),0) | L10: =IF(Debt_M!A10<>"",Debt_M!I10,"")
D11: =IF(Cashflow_M!A11<>"",Cashflow_M!A11,"") | E11: =IF(Cashflow_M!A11<>"",Cashflow_M!G11,"") | F11: =IF(Cashflow_M!A11<>"",Cashflow_M!A11,"") | G11: =IF(Cashflow_M!A11<>"",Cashflow_M!K11,"") | H11: =IF(Cashflow_M!A11<>"",Cashflow_M!D11+Cashflow_M!H11,"") | I11: =IF(Cashflow_M!A11<>"",Cashflow_M!E11+Cashflow_M!F11+Cashflow_M!I11+Cashflow_M!J11,"") | J11: =IF(Cashflow_M!A11<>"",H11-I11,"") | K11: =IF(Cashflow_M!C11="Operation",ABS(Cashflow_M!H11),0) | L11: =IF(Debt_M!A11<>"",Debt_M!I11,"")
A12: CHECKS | D12: =IF(Cashflow_M!A12<>"",Cashflow_M!A12,"") | E12: =IF(Cashflow_M!A12<>"",Cashflow_M!G12,"") | F12: =IF(Cashflow_M!A12<>"",Cashflow_M!A12,"") | G12: =IF(Cashflow_M!A12<>"",Cashflow_M!K12,"") | H12: =IF(Cashflow_M!A12<>"",Cashflow_M!D12+Cashflow_M!H12,"") | I12: =IF(Cashflow_M!A12<>"",Cashflow_M!E12+Cashflow_M!F12+Cashflow_M!I12+Cashflow_M!J12,"") | J12: =IF(Cashflow_M!A12<>"",H12-I12,"") | K12: =IF(Cashflow_M!C12="Operation",ABS(Cashflow_M!H12),0) | L12: =IF(Debt_M!A12<>"",Debt_M!I12,"")
A13: Sources = Uses (Monthly) | B13: =IF(MAX(ABS(J2:J501))<0.01,"PASS","FAIL") | C13: =IF(B{row}="PASS","✓","✗") | D13: =IF(Cashflow_M!A13<>"",Cashflow_M!A13,"") | E13: =IF(Cashflow_M!A13<>"",Cashflow_M!G13,"") | F13: =IF(Cashflow_M!A13<>"",Cashflow_M!A13,"") | G13: =IF(Cashflow_M!A13<>"",Cashflow_M!K13,"") | H13: =IF(Cashflow_M!A13<>"",Cashflow_M!D13+Cashflow_M!H13,"") | I13: =IF(Cashflow_M!A13<>"",Cashflow_M!E13+Cashflow_M!F13+Cashflow_M!I13+Cashflow_M!J13,"") | J13: =IF(Cashflow_M!A13<>"",H13-I13,"") | K13: =IF(Cashflow_M!C13="Operation",ABS(Cashflow_M!H13),0) | L13: =IF(Debt_M!A13<>"",Debt_M!I13,"")
A14: Debt Draw After COD = 0 | B14: =IF(MAX(K2:K501)<0.01,"PASS","FAIL") | C14: =IF(B{row}="PASS","✓","✗") | D14: =IF(Cashflow_M!A14<>"",Cashflow_M!A14,"") | E14: =IF(Cashflow_M!A14<>"",Cashflow_M!G14,"") | F14: =IF(Cashflow_M!A14<>"",Cashflow_M!A14,"") | G14: =IF(Cashflow_M!A14<>"",Cashflow_M!K14,"") | H14: =IF(Cashflow_M!A14<>"",Cashflow_M!D14+Cashflow_M!H14,"") | I14: =IF(Cashflow_M!A14<>"",Cashflow_M!E14+Cashflow_M!F14+Cashflow_M!I14+Cashflow_M!J14,"") | J14: =IF(Cashflow_M!A14<>"",H14-I14,"") | K14: =IF(Cashflow_M!C14="Operation",ABS(Cashflow_M!H14),0) | L14: =IF(Debt_M!A14<>"",Debt_M!I14,"")
A15: Debt Balance >= 0 | B15: =IF(MIN(L2:L501)>=0,"PASS","FAIL") | C15: =IF(B{row}="PASS","✓","✗") | D15: =IF(Cashflow_M!A15<>"",Cashflow_M!A15,"") | E15: =IF(Cashflow_M!A15<>"",Cashflow_M!G15,"") | F15: =IF(Cashflow_M!A15<>"",Cashflow_M!A15,"") | G15: =IF(Cashflow_M!A15<>"",Cashflow_M!K15,"") | H15: =IF(Cashflow_M!A15<>"",Cashflow_M!D15+Cashflow_M!H15,"") | I15: =IF(Cashflow_M!A15<>"",Cashflow_M!E15+Cashflow_M!F15+Cashflow_M!I15+Cashflow_M!J15,"") | J15: =IF(Cashflow_M!A15<>"",H15-I15,"") | K15: =IF(Cashflow_M!C15="Operation",ABS(Cashflow_M!H15),0) | L15: =IF(Debt_M!A15<>"",Debt_M!I15,"")
A16: CAPEX Total Matches Inputs | B16: =IF(ABS(SUM(CAPEX_M!G:G)-(CapexDev+CapexCon+CapexCOD))<1000,"PASS","FAIL") | C16: =IF(B{row}="PASS","✓","✗") | D16: =IF(Cashflow_M!A16<>"",Cashflow_M!A16,"") | E16: =IF(Cashflow_M!A16<>"",Cashflow_M!G16,"") | F16: =IF(Cashflow_M!A16<>"",Cashflow_M!A16,"") | G16: =IF(Cashflow_M!A16<>"",Cashflow_M!K16,"") | H16: =IF(Cashflow_M!A16<>"",Cashflow_M!D16+Cashflow_M!H16,"") | I16: =IF(Cashflow_M!A16<>"",Cashflow_M!E16+Cashflow_M!F16+Cashflow_M!I16+Cashflow_M!J16,"") | J16: =IF(Cashflow_M!A16<>"",H16-I16,"") | K16: =IF(Cashflow_M!C16="Operation",ABS(Cashflow_M!H16),0) | L16: =IF(Debt_M!A16<>"",Debt_M!I16,"")
D17: =IF(Cashflow_M!A17<>"",Cashflow_M!A17,"") | E17: =IF(Cashflow_M!A17<>"",Cashflow_M!G17,"") | F17: =IF(Cashflow_M!A17<>"",Cashflow_M!A17,"") | G17: =IF(Cashflow_M!A17<>"",Cashflow_M!K17,"") | H17: =IF(Cashflow_M!A17<>"",Cashflow_M!D17+Cashflow_M!H17,"") | I17: =IF(Cashflow_M!A17<>"",Cashflow_M!E17+Cashflow_M!F17+Cashflow_M!I17+Cashflow_M!J17,"") | J17: =IF(Cashflow_M!A17<>"",H17-I17,"") | K17: =IF(Cashflow_M!C17="Operation",ABS(Cashflow_M!H17),0) | L17: =IF(Debt_M!A17<>"",Debt_M!I17,"")
D18: =IF(Cashflow_M!A18<>"",Cashflow_M!A18,"") | E18: =IF(Cashflow_M!A18<>"",Cashflow_M!G18,"") | F18: =IF(Cashflow_M!A18<>"",Cashflow_M!A18,"") | G18: =IF(Cashflow_M!A18<>"",Cashflow_M!K18,"") | H18: =IF(Cashflow_M!A18<>"",Cashflow_M!D18+Cashflow_M!H18,"") | I18: =IF(Cashflow_M!A18<>"",Cashflow_M!E18+Cashflow_M!F18+Cashflow_M!I18+Cashflow_M!J18,"") | J18: =IF(Cashflow_M!A18<>"",H18-I18,"") | K18: =IF(Cashflow_M!C18="Operation",ABS(Cashflow_M!H18),0) | L18: =IF(Debt_M!A18<>"",Debt_M!I18,"")
D19: =IF(Cashflow_M!A19<>"",Cashflow_M!A19,"") | E19: =IF(Cashflow_M!A19<>"",Cashflow_M!G19,"") | F19: =IF(Cashflow_M!A19<>"",Cashflow_M!A19,"") | G19: =IF(Cashflow_M!A19<>"",Cashflow_M!K19,"") | H19: =IF(Cashflow_M!A19<>"",Cashflow_M!D19+Cashflow_M!H19,"") | I19: =IF(Cashflow_M!A19<>"",Cashflow_M!E19+Cashflow_M!F19+Cashflow_M!I19+Cashflow_M!J19,"") | J19: =IF(Cashflow_M!A19<>"",H19-I19,"") | K19: =IF(Cashflow_M!C19="Operation",ABS(Cashflow_M!H19),0) | L19: =IF(Debt_M!A19<>"",Debt_M!I19,"")
D20: =IF(Cashflow_M!A20<>"",Cashflow_M!A20,"") | E20: =IF(Cashflow_M!A20<>"",Cashflow_M!G20,"") | F20: =IF(Cashflow_M!A20<>"",Cashflow_M!A20,"") | G20: =IF(Cashflow_M!A20<>"",Cashflow_M!K20,"") | H20: =IF(Cashflow_M!A20<>"",Cashflow_M!D20+Cashflow_M!H20,"") | I20: =IF(Cashflow_M!A20<>"",Cashflow_M!E20+Cashflow_M!F20+Cashflow_M!I20+Cashflow_M!J20,"") | J20: =IF(Cashflow_M!A20<>"",H20-I20,"") | K20: =IF(Cashflow_M!C20="Operation",ABS(Cashflow_M!H20),0) | L20: =IF(Debt_M!A20<>"",Debt_M!I20,"")
D21: =IF(Cashflow_M!A21<>"",Cashflow_M!A21,"") | E21: =IF(Cashflow_M!A21<>"",Cashflow_M!G21,"") | F21: =IF(Cashflow_M!A21<>"",Cashflow_M!A21,"") | G21: =IF(Cashflow_M!A21<>"",Cashflow_M!K21,"") | H21: =IF(Cashflow_M!A21<>"",Cashflow_M!D21+Cashflow_M!H21,"") | I21: =IF(Cashflow_M!A21<>"",Cashflow_M!E21+Cashflow_M!F21+Cashflow_M!I21+Cashflow_M!J21,"") | J21: =IF(Cashflow_M!A21<>"",H21-I21,"") | K21: =IF(Cashflow_M!C21="Operation",ABS(Cashflow_M!H21),0) | L21: =IF(Debt_M!A21<>"",Debt_M!I21,"")
D22: =IF(Cashflow_M!A22<>"",Cashflow_M!A22,"") | E22: =IF(Cashflow_M!A22<>"",Cashflow_M!G22,"") | F22: =IF(Cashflow_M!A22<>"",Cashflow_M!A22,"") | G22: =IF(Cashflow_M!A22<>"",Cashflow_M!K22,"") | H22: =IF(Cashflow_M!A22<>"",Cashflow_M!D22+Cashflow_M!H22,"") | I22: =IF(Cashflow_M!A22<>"",Cashflow_M!E22+Cashflow_M!F22+Cashflow_M!I22+Cashflow_M!J22,"") | J22: =IF(Cashflow_M!A22<>"",H22-I22,"") | K22: =IF(Cashflow_M!C22="Operation",ABS(Cashflow_M!H22),0) | L22: =IF(Debt_M!A22<>"",Debt_M!I22,"")
D23: =IF(Cashflow_M!A23<>"",Cashflow_M!A23,"") | E23: =IF(Cashflow_M!A23<>"",Cashflow_M!G23,"") | F23: =IF(Cashflow_M!A23<>"",Cashflow_M!A23,"") | G23: =IF(Cashflow_M!A23<>"",Cashflow_M!K23,"") | H23: =IF(Cashflow_M!A23<>"",Cashflow_M!D23+Cashflow_M!H23,"") | I23: =IF(Cashflow_M!A23<>"",Cashflow_M!E23+Cashflow_M!F23+Cashflow_M!I23+Cashflow_M!J23,"") | J23: =IF(Cashflow_M!A23<>"",H23-I23,"") | K23: =IF(Cashflow_M!C23="Operation",ABS(Cashflow_M!H23),0) | L23: =IF(Debt_M!A23<>"",Debt_M!I23,"")
D24: =IF(Cashflow_M!A24<>"",Cashflow_M!A24,"") | E24: =IF(Cashflow_M!A24<>"",Cashflow_M!G24,"") | F24: =IF(Cashflow_M!A24<>"",Cashflow_M!A24,"") | G24: =IF(Cashflow_M!A24<>"",Cashflow_M!K24,"") | H24: =IF(Cashflow_M!A24<>"",Cashflow_M!D24+Cashflow_M!H24,"") | I24: =IF(Cashflow_M!A24<>"",Cashflow_M!E24+Cashflow_M!F24+Cashflow_M!I24+Cashflow_M!J24,"") | J24: =IF(Cashflow_M!A24<>"",H24-I24,"") | K24: =IF(Cashflow_M!C24="Operation",ABS(Cashflow_M!H24),0) | L24: =IF(Debt_M!A24<>"",Debt_M!I24,"")
D25: =IF(Cashflow_M!A25<>"",Cashflow_M!A25,"") | E25: =IF(Cashflow_M!A25<>"",Cashflow_M!G25,"") | F25: =IF(Cashflow_M!A25<>"",Cashflow_M!A25,"") | G25: =IF(Cashflow_M!A25<>"",Cashflow_M!K25,"") | H25: =IF(Cashflow_M!A25<>"",Cashflow_M!D25+Cashflow_M!H25,"") | I25: =IF(Cashflow_M!A25<>"",Cashflow_M!E25+Cashflow_M!F25+Cashflow_M!I25+Cashflow_M!J25,"") | J25: =IF(Cashflow_M!A25<>"",H25-I25,"") | K25: =IF(Cashflow_M!C25="Operation",ABS(Cashflow_M!H25),0) | L25: =IF(Debt_M!A25<>"",Debt_M!I25,"")
D26: =IF(Cashflow_M!A26<>"",Cashflow_M!A26,"") | E26: =IF(Cashflow_M!A26<>"",Cashflow_M!G26,"") | F26: =IF(Cashflow_M!A26<>"",Cashflow_M!A26,"") | G26: =IF(Cashflow_M!A26<>"",Cashflow_M!K26,"") | H26: =IF(Cashflow_M!A26<>"",Cashflow_M!D26+Cashflow_M!H26,"") | I26: =IF(Cashflow_M!A26<>"",Cashflow_M!E26+Cashflow_M!F26+Cashflow_M!I26+Cashflow_M!J26,"") | J26: =IF(Cashflow_M!A26<>"",H26-I26,"") | K26: =IF(Cashflow_M!C26="Operation",ABS(Cashflow_M!H26),0) | L26: =IF(Debt_M!A26<>"",Debt_M!I26,"")
D27: =IF(Cashflow_M!A27<>"",Cashflow_M!A27,"") | E27: =IF(Cashflow_M!A27<>"",Cashflow_M!G27,"") | F27: =IF(Cashflow_M!A27<>"",Cashflow_M!A27,"") | G27: =IF(Cashflow_M!A27<>"",Cashflow_M!K27,"") | H27: =IF(Cashflow_M!A27<>"",Cashflow_M!D27+Cashflow_M!H27,"") | I27: =IF(Cashflow_M!A27<>"",Cashflow_M!E27+Cashflow_M!F27+Cashflow_M!I27+Cashflow_M!J27,"") | J27: =IF(Cashflow_M!A27<>"",H27-I27,"") | K27: =IF(Cashflow_M!C27="Operation",ABS(Cashflow_M!H27),0) | L27: =IF(Debt_M!A27<>"",Debt_M!I27,"")
D28: =IF(Cashflow_M!A28<>"",Cashflow_M!A28,"") | E28: =IF(Cashflow_M!A28<>"",Cashflow_M!G28,"") | F28: =IF(Cashflow_M!A28<>"",Cashflow_M!A28,"") | G28: =IF(Cashflow_M!A28<>"",Cashflow_M!K28,"") | H28: =IF(Cashflow_M!A28<>"",Cashflow_M!D28+Cashflow_M!H28,"") | I28: =IF(Cashflow_M!A28<>"",Cashflow_M!E28+Cashflow_M!F28+Cashflow_M!I28+Cashflow_M!J28,"") | J28: =IF(Cashflow_M!A28<>"",H28-I28,"") | K28: =IF(Cashflow_M!C28="Operation",ABS(Cashflow_M!H28),0) | L28: =IF(Debt_M!A28<>"",Debt_M!I28,"")
... D501: =IF(Cashflow_M!A501<>"",Cashflow_M!A501,"") | E501: =IF(Cashflow_M!A501<>"",Cashflow_M!G501,"") | F501: =IF(Cashflow_M!A501<>"",Cashflow_M!A501,"") | G501: =IF(Cashflow_M!A501<>"",Cashflow_M!K501,"") | H501: =IF(Cashflow_M!A501<>"",Cashflow_M!D501+Cashflow_M!H501,"") | I501: =IF(Cashflow_M!A501<>"",Cashflow_M!E501+Cashflow_M!F501+Cashflow_M!I501+Cashflow_M!J501,"") | J501: =IF(Cashflow_M!A501<>"",H501-I501,"") | K501: =IF(Cashflow_M!C501="Operation",ABS(Cashflow_M!H501),0) | L501: =IF(Debt_M!A501<>"",Debt_M!I501,"")
